{"2018-00000649": {"category": "Drug", "address": "2200 BAKER DR Boulder CO", "date": "02/23/2018 23:36 - 02/23/2018 23:36"}}
{"2018-00000649": {"category": "Drug", "address": "2200 BAKER DR Boulder CO", "date": "02/23/2018 23:36 - 02/23/2018 23:36"}}
{"2018-00000650": {"category": "Alcohol", "address": "1720 UNIVERSITY AVE Boulder CO", "date": "02/24/2018 01:04 - 02/24/2018 02:14"}}
{"2018-00000651": {"category": "DUI/DWAI", "address": "30TH ST /  BASELINE RD Boulder CO", "date": "02/24/2018 00:52 - 02/24/2018 03:00"}}
{"2018-00000651": {"category": "DUI/DWAI", "address": "30TH ST /  BASELINE RD Boulder CO", "date": "02/24/2018 00:52 - 02/24/2018 03:00"}}
{"2018-00000652": {"category": "Drug", "address": "2525 KITTREDGE LOOP DR Boulder CO", "date": "02/24/2018 02:02 - 02/24/2018 02:17"}}
{"2018-00000653": {"category": "Criminal", "address": "2115 BAKER DR Boulder CO", "date": "02/24/2018 02:11 - 02/24/2018 03:27"}}
{"2018-00000653": {"category": "Criminal", "address": "2115 BAKER DR Boulder CO", "date": "02/24/2018 02:11 - 02/24/2018 03:27"}}
{"2018-00000655": {"category": "Alcohol", "address": "600 30TH ST Boulder CO", "date": "02/24/2018 02:27 - 02/24/2018 02:27"}}
{"2018-00000655": {"category": "Alcohol", "address": "600 30TH ST Boulder CO", "date": "02/24/2018 02:27 - 02/24/2018 02:27"}}
{"2018-00000657": {"category": "Alcohol", "address": "2525 KITTREDGE LOOP DR Boulder CO", "date": "02/24/2018 05:14 - 02/24/2018 06:30"}}
{"2018-00000658": {"category": "Drug", "address": "600 30TH ST Boulder CO", "date": "02/24/2018 21:21 - 02/24/2018 21:38"}}
{"2018-00000658": {"category": "Drug", "address": "600 30TH ST Boulder CO", "date": "02/24/2018 21:21 - 02/24/2018 21:38"}}
{"2018-00000660": {"category": "Alcohol", "address": "3300 BASELINE RD Boulder CO", "date": "02/24/2018 21:52 - 02/24/2018 22:02"}}
{"2018-00000661": {"category": "Alcohol", "address": "1720 UNIVERSITY AVE Boulder CO", "date": "02/24/2018 22:56 - 02/24/2018 23:16"}}
{"2018-00000663": {"category": "Alcohol", "address": "2005 BAKER DR Boulder CO", "date": "02/24/2018 23:04 - 02/24/2018 23:30"}}
{"2017-00003191": {"category": "Assault", "address": "4747 ARAPAHOE AVE Boulder CO", "date": "12/01/2017 19:02 - 12/01/2017 19:02"}}
{"2017-00003191": {"category": "Assault", "address": "4747 ARAPAHOE AVE Boulder CO", "date": "12/01/2017 19:02 - 12/01/2017 19:02"}}
{"2017-00003191": {"category": "Assault", "address": "4747 ARAPAHOE AVE Boulder CO", "date": "12/01/2017 19:02 - 12/01/2017 19:02"}}
{"2018-00000368": {"category": "DUI/DWAI", "address": "BASELINE RD /  BROADWAY Boulder CO", "date": "02/04/2018 23:51 - 02/05/2018 02:50"}}
{"2018-00000368": {"category": "DUI/DWAI", "address": "BASELINE RD /  BROADWAY Boulder CO", "date": "02/04/2018 23:51 - 02/05/2018 02:50"}}
{"2018-00000368": {"category": "DUI/DWAI", "address": "BASELINE RD /  BROADWAY Boulder CO", "date": "02/04/2018 23:51 - 02/05/2018 02:50"}}
{"2018-00000368": {"category": "DUI/DWAI", "address": "BASELINE RD /  BROADWAY Boulder CO", "date": "02/04/2018 23:51 - 02/05/2018 02:50"}}
{"2018-00000368": {"category": "DUI/DWAI", "address": "BASELINE RD /  BROADWAY Boulder CO", "date": "02/04/2018 23:51 - 02/05/2018 02:50"}}
{"2018-00000368": {"category": "DUI/DWAI", "address": "BASELINE RD /  BROADWAY Boulder CO", "date": "02/04/2018 23:51 - 02/05/2018 02:50"}}
{"2018-00000369": {"category": "Drug", "address": "1546 BROADWAY Boulder CO", "date": "02/05/2018 02:20 - 02/05/2018 03:20"}}
{"2018-00000369": {"category": "Drug", "address": "1546 BROADWAY Boulder CO", "date": "02/05/2018 02:20 - 02/05/2018 03:20"}}
{"2018-00000369": {"category": "Drug", "address": "1546 BROADWAY Boulder CO", "date": "02/05/2018 02:20 - 02/05/2018 03:20"}}
{"2018-00000372": {"category": "Disturbance", "address": "510 30TH ST Boulder CO", "date": "02/05/2018 18:11 - 02/05/2018 18:11"}}
{"2018-00000374": {"category": "Drug", "address": "2250 WILLARD LOOP DR Boulder CO", "date": "02/05/2018 20:20 - 02/05/2018 20:58"}}
{"2018-00000374": {"category": "Drug", "address": "2250 WILLARD LOOP DR Boulder CO", "date": "02/05/2018 20:20 - 02/05/2018 20:58"}}
{"2018-00000375": {"category": "Drug", "address": "500 30TH ST Boulder CO", "date": "02/05/2018 21:19 - 02/05/2018 21:45"}}
{"2018-00000376": {"category": "Drug", "address": "3300 BASELINE RD Boulder CO", "date": "02/05/2018 22:16 - 02/05/2018 23:25"}}
{"2018-00000376": {"category": "Drug", "address": "3300 BASELINE RD Boulder CO", "date": "02/05/2018 22:16 - 02/05/2018 23:25"}}
{"2018-00008088": {"category": "Theft", "address": "1905 COLORADO AVE Boulder CO", "date": "02/05/2018 17:40 - 02/05/2018 17:40"}}
{"2018-00008088": {"category": "Theft", "address": "1905 COLORADO AVE Boulder CO", "date": "02/05/2018 17:40 - 02/05/2018 17:40"}}
{"2018-00000526": {"category": "Alcohol", "address": "18TH ST /  COLORADO AVE Boulder CO", "date": "02/16/2018 01:08 - 02/16/2018 01:15"}}
{"2018-00000526": {"category": "Alcohol", "address": "18TH ST /  COLORADO AVE Boulder CO", "date": "02/16/2018 01:08 - 02/16/2018 01:15"}}
{"2018-00000529": {"category": "Other", "address": "1720 UNIVERSITY AVE Boulder CO", "date": "02/16/2018 01:36 - 02/16/2018 04:04"}}
{"2018-00000530": {"category": "Alcohol", "address": "1720 UNIVERSITY AVE Boulder CO", "date": "02/16/2018 03:30 - 02/16/2018 03:30"}}
{"2018-00000531": {"category": "Criminal", "address": "1481 FOLSOM ST Boulder CO", "date": "02/15/2018 22:00 - 02/16/2018 07:00"}}
{"2018-00000531": {"category": "Criminal", "address": "1481 FOLSOM ST Boulder CO", "date": "02/15/2018 22:00 - 02/16/2018 07:00"}}
{"2018-00000531": {"category": "Criminal", "address": "1481 FOLSOM ST Boulder CO", "date": "02/15/2018 22:00 - 02/16/2018 07:00"}}
{"2018-00000533": {"category": "Criminal", "address": "1402 BROADWAY Boulder CO", "date": "02/16/2018 10:13 - 02/16/2018 10:13"}}
{"2018-00000535": {"category": "Fraud/Forgery", "address": "2200 WILLARD LOOP DR Boulder CO", "date": "02/16/2018 01:45 - 02/16/2018 01:45"}}
{"2018-00000539": {"category": "Traffic", "address": "1475 FOLSOM ST Boulder CO", "date": "02/16/2018 14:22 - 02/16/2018 14:22"}}
{"2018-00000540": {"category": "Drug", "address": "1111 ENGINEERING DR Boulder CO", "date": "02/16/2018 14:30 - 02/16/2018 14:30"}}
{"2018-00000540": {"category": "Drug", "address": "1111 ENGINEERING DR Boulder CO", "date": "02/16/2018 14:30 - 02/16/2018 14:30"}}
{"2018-00000541": {"category": "Theft", "address": "2450 KITTREDGE LOOP DR Boulder CO", "date": "02/16/2018 16:00 - 02/16/2018 16:00"}}
{"2018-00000547": {"category": "Criminal", "address": "2085 COLORADO AVE Boulder CO", "date": "02/16/2018 23:12 - 02/16/2018 23:12"}}
{"2018-00008017": {"category": "Theft", "address": "2200 BAKER DR Boulder CO", "date": "12/21/2017 10:45 - 01/13/2018 10:45"}}
{"2018-00008017": {"category": "Theft", "address": "2200 BAKER DR Boulder CO", "date": "12/21/2017 10:45 - 01/13/2018 10:45"}}
{"2018-00008123": {"category": "Theft", "address": "1855 PLEASANT ST Boulder CO", "date": "02/15/2018 21:19 - 02/15/2018 23:02"}}
{"2018-00000488": {"category": "Other", "address": "2450 KITTREDGE LOOP DR Boulder CO", "date": "02/13/2018 14:45 - 02/13/2018 14:45"}}
{"2018-00000714": {"category": "Warrant", "address": "2085 COLORADO AVE Boulder CO", "date": "03/01/2018 23:32 - 03/01/2018 23:32"}}
{"2018-00000714": {"category": "Warrant", "address": "2085 COLORADO AVE Boulder CO", "date": "03/01/2018 23:32 - 03/01/2018 23:32"}}
{"2018-00000714": {"category": "Warrant", "address": "2085 COLORADO AVE Boulder CO", "date": "03/01/2018 23:32 - 03/01/2018 23:32"}}
{"2018-00000714": {"category": "Warrant", "address": "2085 COLORADO AVE Boulder CO", "date": "03/01/2018 23:32 - 03/01/2018 23:32"}}
{"2018-00000714": {"category": "Warrant", "address": "2085 COLORADO AVE Boulder CO", "date": "03/01/2018 23:32 - 03/01/2018 23:32"}}
{"2018-00000714": {"category": "Warrant", "address": "2085 COLORADO AVE Boulder CO", "date": "03/01/2018 23:32 - 03/01/2018 23:32"}}
{"2018-00000715": {"category": "Alcohol", "address": "1550 CENTRAL CAMPUS Boulder CO", "date": "03/02/2018 00:55 - 03/02/2018 00:55"}}
{"2018-00000716": {"category": "Alcohol", "address": "1020 18TH ST Boulder CO", "date": "03/02/2018 01:30 - 03/02/2018 01:30"}}
{"2018-00000717": {"category": "Alcohol", "address": "600 30TH ST Boulder CO", "date": "03/02/2018 01:38 - 03/02/2018 01:38"}}
{"2018-00000717": {"category": "Alcohol", "address": "600 30TH ST Boulder CO", "date": "03/02/2018 01:38 - 03/02/2018 01:38"}}
{"2018-00000718": {"category": "Other", "address": "1030 BROADWAY Boulder CO", "date": "03/02/2018 02:30 - 03/02/2018 02:30"}}
{"2018-00000719": {"category": "Other", "address": "3180 BASELINE RD Boulder CO", "date": "03/02/2018 23:45 - 03/02/2018 23:45"}}
{"2018-00000720": {"category": "Fraud/Forgery", "address": "1610 PLEASANT ST Boulder CO", "date": "03/02/2018 10:40 - 03/02/2018 10:40"}}
{"2018-00000721": {"category": "Theft", "address": "3215 MARINE ST Boulder CO", "date": "02/21/2018 11:08 - 03/02/2018 11:08"}}
{"2018-00000722": {"category": "Theft", "address": "1157 18TH ST Boulder CO", "date": "03/02/2018 13:36 - 03/02/2018 13:36"}}
{"2018-00000723": {"category": "Traffic", "address": "2180 REGENT DR Boulder CO", "date": "03/02/2018 14:39 - 03/02/2018 14:39"}}
{"2018-00000724": {"category": "Criminal", "address": "1610 PLEASANT ST Boulder CO", "date": "03/02/2018 15:57 - 03/02/2018 15:57"}}
{"2018-00000725": {"category": "Warrant", "address": "1715 UNIVERSITY AVE Boulder CO", "date": "03/02/2018 16:38 - 03/02/2018 16:38"}}
{"2018-00000728": {"category": "Drug", "address": "500 30TH ST Boulder CO", "date": "03/02/2018 21:42 - 03/02/2018 22:05"}}
{"2018-00000728": {"category": "Drug", "address": "500 30TH ST Boulder CO", "date": "03/02/2018 21:42 - 03/02/2018 22:05"}}
{"2018-00000623": {"category": "Fraud/Forgery", "address": "2249 WILLARD LOOP DR Boulder CO", "date": "02/16/2018 04:35 - 02/16/2018 04:35"}}
{"2018-00000682": {"category": "Criminal", "address": "2005 BAKER DR Boulder CO", "date": "02/27/2018 01:00 - 02/27/2018 02:00"}}
{"2018-00000683": {"category": "Traffic", "address": "REGENT DR /  COLORADO Boulder CO", "date": "02/27/2018 10:05 - 02/27/2018 10:05"}}
{"2018-00000684": {"category": "Fraud/Forgery", "address": "1720 UNIVERSITY AVE Boulder CO", "date": "02/27/2018 11:45 - 02/27/2018 11:45"}}
{"2018-00000685": {"category": "Traffic", "address": "3359 APACHE RD Boulder CO", "date": "02/27/2018 08:40 - 02/27/2018 08:40"}}
{"2018-00000687": {"category": "Drug", "address": "1720 UNIVERSITY AVE Boulder CO", "date": "02/27/2018 20:01 - 02/27/2018 20:50"}}
{"2018-00000691": {"category": "Drug", "address": "600 30TH ST Boulder CO", "date": "02/27/2018 22:11 - 02/27/2018 22:30"}}
{"2018-00000692": {"category": "Alcohol", "address": "2200 WILLARD LOOP DR Boulder CO", "date": "02/27/2018 22:37 - 02/27/2018 22:37"}}
{"2018-00000695": {"category": "Drug", "address": "3300 BASELINE RD Boulder CO", "date": "02/27/2018 18:00 - 02/27/2018 23:25"}}
{"2018-00000695": {"category": "Drug", "address": "3300 BASELINE RD Boulder CO", "date": "02/27/2018 18:00 - 02/27/2018 23:25"}}
{"2018-00008145": {"category": "Theft", "address": "2005 BAKER DR Boulder CO", "date": "02/26/2018 12:45 - 02/27/2018 12:45"}}
{"2018-00008145": {"category": "Theft", "address": "2005 BAKER DR Boulder CO", "date": "02/26/2018 12:45 - 02/27/2018 12:45"}}
{"2018-00000549": {"category": "Alcohol", "address": "960 GREEN MOUNTAIN DR Boulder CO", "date": "02/17/2018 00:15 - 02/17/2018 00:15"}}
{"2018-00000553": {"category": "Alcohol", "address": "2400 KITTREDGE LOOP DR Boulder CO", "date": "02/17/2018 00:25 - 02/17/2018 00:30"}}
{"2018-00000554": {"category": "Criminal", "address": "3400 BASELINE RD Boulder CO", "date": "02/17/2018 00:33 - 02/17/2018 00:33"}}
{"2018-00000556": {"category": "Alcohol", "address": "2005 BAKER DR Boulder CO", "date": "02/17/2018 02:15 - 02/17/2018 02:15"}}
{"2018-00000558": {"category": "Other", "address": "2249 WILLARD LOOP DR Boulder CO", "date": "02/17/2018 07:00 - 02/17/2018 07:00"}}
{"2018-00000559": {"category": "Alcohol", "address": "2005 BAKER DR Boulder CO", "date": "02/17/2018 12:30 - 02/17/2018 12:30"}}
{"2018-00000562": {"category": "Assault", "address": "1300 30TH ST Boulder CO", "date": "02/17/2018 13:16 - 02/17/2018 13:16"}}
{"2018-00000562": {"category": "Assault", "address": "1300 30TH ST Boulder CO", "date": "02/17/2018 13:16 - 02/17/2018 13:16"}}
{"2018-00000563": {"category": "Warrant", "address": "1669 EUCLID AVE Boulder CO", "date": "02/17/2018 14:00 - 02/17/2018 14:00"}}
{"2018-00000564": {"category": "Alcohol", "address": "555 30TH ST Boulder CO", "date": "02/17/2018 15:42 - 02/17/2018 15:42"}}
{"2018-00000566": {"category": "Info", "address": "2005 BAKER DR Boulder CO", "date": "02/17/2018 19:19 - 02/17/2018 19:19"}}
{"2018-00000568": {"category": "Drug", "address": "2250 WILLARD LOOP DR Boulder CO", "date": "02/17/2018 20:57 - 02/17/2018 21:14"}}
{"2018-00000569": {"category": "Alcohol", "address": "2115 BAKER DR Boulder CO", "date": "02/17/2018 21:26 - 02/17/2018 21:40"}}
{"2018-00000570": {"category": "Alcohol", "address": "2115 BAKER DR Boulder CO", "date": "02/17/2018 21:48 - 02/17/2018 22:04"}}
{"2018-00000572": {"category": "Drug", "address": "2200 WILLARD LOOP DR Boulder CO", "date": "02/17/2018 23:37 - 02/18/2018 00:42"}}
{"2018-00008090": {"category": "Criminal", "address": "600 30TH ST Boulder CO", "date": "02/05/2018 08:42 - 02/05/2018 11:50"}}
{"2018-00008093": {"category": "Theft", "address": "2525 KITTREDGE LOOP DR Boulder CO", "date": "02/05/2018 21:40 - 02/06/2018 21:40"}}
{"2018-00008101": {"category": "Theft", "address": "2250 WILLARD LOOP DR Boulder CO", "date": "02/08/2018 10:30 - 02/08/2018 15:45"}}
{"2018-00008107": {"category": "Criminal", "address": "960 GREEN MOUNTAIN DR Boulder CO", "date": "02/11/2018 21:30 - 02/11/2018 21:30"}}
{"2018-00008114": {"category": "Criminal", "address": "1720 UNIVERSITY AVE Boulder CO", "date": "02/13/2018 09:00 - 02/13/2018 12:00"}}
{"2018-00008114": {"category": "Criminal", "address": "1720 UNIVERSITY AVE Boulder CO", "date": "02/13/2018 09:00 - 02/13/2018 12:00"}}
{"2018-00008115": {"category": "Theft", "address": "2480 KITTREDGE LOOP DR Boulder CO", "date": "02/08/2018 12:30 - 02/08/2018 20:30"}}
{"2018-00000693": {"category": "Theft", "address": "2005 BAKER DR Boulder CO", "date": "02/27/2018 23:20 - 02/27/2018 23:35"}}
{"2018-00000707": {"category": "Theft", "address": "500 30TH ST Boulder CO", "date": "02/28/2018 23:45 - 03/01/2018 02:00"}}
{"2018-00000707": {"category": "Theft", "address": "500 30TH ST Boulder CO", "date": "02/28/2018 23:45 - 03/01/2018 02:00"}}
{"2018-00000707": {"category": "Theft", "address": "500 30TH ST Boulder CO", "date": "02/28/2018 23:45 - 03/01/2018 02:00"}}
{"2018-00000707": {"category": "Theft", "address": "500 30TH ST Boulder CO", "date": "02/28/2018 23:45 - 03/01/2018 02:00"}}
{"2018-00000709": {"category": "Warrant", "address": "3100 MARINE ST Boulder CO", "date": "03/01/2018 13:30 - 03/01/2018 13:30"}}
{"2018-00000710": {"category": "Drug", "address": "1720 UNIVERSITY AVE Boulder CO", "date": "03/01/2018 20:16 - 03/01/2018 20:24"}}
{"2018-00000711": {"category": "Traffic", "address": "COLORADO AVE /  REGENT Boulder CO", "date": "03/01/2018 20:30 - 03/01/2018 20:30"}}
{"2018-00000711": {"category": "Traffic", "address": "COLORADO AVE /  REGENT Boulder CO", "date": "03/01/2018 20:30 - 03/01/2018 20:30"}}
{"2018-00000712": {"category": "Drug", "address": "2115 BAKER DR Boulder CO", "date": "03/01/2018 21:02 - 03/01/2018 21:40"}}
{"2018-00000712": {"category": "Drug", "address": "2115 BAKER DR Boulder CO", "date": "03/01/2018 21:02 - 03/01/2018 21:40"}}
{"2018-00000713": {"category": "Alcohol", "address": "600 30TH ST Boulder CO", "date": "03/01/2018 21:47 - 03/01/2018 21:54"}}
{"2018-00008152": {"category": "Theft", "address": "2400 KITTREDGE LOOP DR Boulder CO", "date": "03/01/2018 10:00 - 03/01/2018 10:00"}}
{"2018-00000271": {"category": "Assault", "address": "960 GREEN MOUNTAIN DR Boulder CO", "date": "01/28/2018 04:25 - 01/28/2018 05:00"}}
{"2018-00000271": {"category": "Assault", "address": "960 GREEN MOUNTAIN DR Boulder CO", "date": "01/28/2018 04:25 - 01/28/2018 05:00"}}
{"2018-00000271": {"category": "Assault", "address": "960 GREEN MOUNTAIN DR Boulder CO", "date": "01/28/2018 04:25 - 01/28/2018 05:00"}}
{"2018-00000391": {"category": "Assault", "address": "2005 BAKER DR Boulder CO", "date": "02/06/2018 17:00 - 02/06/2018 18:00"}}
{"2018-00000391": {"category": "Assault", "address": "2005 BAKER DR Boulder CO", "date": "02/06/2018 17:00 - 02/06/2018 18:00"}}
{"2018-00000392": {"category": "Drug", "address": "1720 UNIVERSITY AVE Boulder CO", "date": "02/07/2018 01:42 - 02/07/2018 01:42"}}
{"2018-00000392": {"category": "Drug", "address": "1720 UNIVERSITY AVE Boulder CO", "date": "02/07/2018 01:42 - 02/07/2018 01:42"}}
{"2018-00000395": {"category": "Traffic", "address": "900 REGENT DR Boulder CO", "date": "02/07/2018 18:28 - 02/07/2018 19:10"}}
{"2018-00000398": {"category": "Alcohol", "address": "2250 WILLARD LOOP DR Boulder CO", "date": "02/07/2018 22:57 - 02/07/2018 23:22"}}
{"2018-00000399": {"category": "Drug", "address": "500 30TH ST Boulder CO", "date": "02/07/2018 23:09 - 02/07/2018 23:59"}}
{"2018-00000566": {"category": "Info", "address": "2005 BAKER DR Boulder CO", "date": "02/17/2018 19:19 - 02/17/2018 19:19"}}
{"2018-00000572": {"category": "Drug", "address": "2200 WILLARD LOOP DR Boulder CO", "date": "02/17/2018 23:37 - 02/18/2018 00:42"}}
{"2018-00000573": {"category": "Drug", "address": "2200 BAKER DR Boulder CO", "date": "02/18/2018 00:03 - 02/18/2018 00:03"}}
{"2018-00000573": {"category": "Drug", "address": "2200 BAKER DR Boulder CO", "date": "02/18/2018 00:03 - 02/18/2018 00:03"}}
{"2018-00000574": {"category": "Alcohol", "address": "18TH ST /  EUCLID AVE Boulder CO", "date": "02/18/2018 01:05 - 02/18/2018 02:07"}}
{"2018-00000577": {"category": "Other", "address": "1521 CENTRAL CAMPUS Boulder CO", "date": "02/18/2018 01:27 - 02/18/2018 01:27"}}
{"2018-00000577": {"category": "Other", "address": "1521 CENTRAL CAMPUS Boulder CO", "date": "02/18/2018 01:27 - 02/18/2018 01:27"}}
{"2018-00000579": {"category": "Alcohol", "address": "500 30TH ST Boulder CO", "date": "02/18/2018 02:00 - 02/18/2018 02:00"}}
{"2018-00000580": {"category": "Alcohol", "address": "2249 WILLARD LOOP DR Boulder CO", "date": "02/18/2018 02:14 - 02/18/2018 02:41"}}
{"2018-00000582": {"category": "Warrant", "address": "3600 CADDO PKY Boulder CO", "date": "02/18/2018 09:04 - 02/18/2018 09:04"}}
{"2018-00000582": {"category": "Warrant", "address": "3600 CADDO PKY Boulder CO", "date": "02/18/2018 09:04 - 02/18/2018 09:04"}}
{"2018-00000582": {"category": "Warrant", "address": "3600 CADDO PKY Boulder CO", "date": "02/18/2018 09:04 - 02/18/2018 09:04"}}
{"2018-00000583": {"category": "Criminal", "address": "2180 REGENT DR Boulder CO", "date": "02/18/2018 11:23 - 02/18/2018 11:23"}}
{"2018-00000635": {"category": "Drug", "address": "2250 WILLARD LOOP DR Boulder CO", "date": "02/23/2018 02:30 - 02/23/2018 02:30"}}
{"2018-00000636": {"category": "Criminal", "address": "600 30TH ST Boulder CO", "date": "02/23/2018 02:49 - 02/23/2018 02:49"}}
{"2018-00000638": {"category": "Traffic", "address": "2360 COLORADO AVE Boulder CO", "date": "02/23/2018 12:11 - 02/23/2018 12:11"}}
{"2018-00000639": {"category": "Alcohol", "address": "2249 WILLARD LOOP DR Boulder CO", "date": "02/23/2018 13:45 - 02/23/2018 13:45"}}
{"2018-00000641": {"category": "Criminal", "address": "1720 UNIVERSITY AVE Boulder CO", "date": "02/18/2018 11:00 - 02/19/2018 00:00"}}
{"2018-00000642": {"category": "Theft", "address": "1669 EUCLID AVE Boulder CO", "date": "02/23/2018 15:10 - 02/23/2018 15:10"}}
{"2018-00000645": {"category": "Drug", "address": "2200 WILLARD LOOP DR Boulder CO", "date": "02/23/2018 21:13 - 02/23/2018 21:45"}}
{"2018-00000645": {"category": "Drug", "address": "2200 WILLARD LOOP DR Boulder CO", "date": "02/23/2018 21:13 - 02/23/2018 21:45"}}
{"2018-00000646": {"category": "Alcohol", "address": "3300 BASELINE RD Boulder CO", "date": "02/23/2018 22:06 - 02/23/2018 22:24"}}
{"2018-00000647": {"category": "Drug", "address": "1720 UNIVERSITY AVE Boulder CO", "date": "02/23/2018 22:43 - 02/23/2018 23:38"}}
{"2018-00000647": {"category": "Drug", "address": "1720 UNIVERSITY AVE Boulder CO", "date": "02/23/2018 22:43 - 02/23/2018 23:38"}}
{"2018-00000647": {"category": "Drug", "address": "1720 UNIVERSITY AVE Boulder CO", "date": "02/23/2018 22:43 - 02/23/2018 23:38"}}
{"2018-00000649": {"category": "Drug", "address": "2200 BAKER DR Boulder CO", "date": "02/23/2018 23:36 - 02/23/2018 23:36"}}
{"2018-00000649": {"category": "Drug", "address": "2200 BAKER DR Boulder CO", "date": "02/23/2018 23:36 - 02/23/2018 23:36"}}
{"2018-00008139": {"category": "Theft", "address": "2590 KITTREDGE LOOP DR Boulder CO", "date": "02/23/2018 06:43 - 02/23/2018 06:43"}}
{"2018-00000343": {"category": "Alcohol", "address": "4001 DISCOVERY DR Boulder CO", "date": "02/03/2018 00:30 - 02/03/2018 00:30"}}
{"2018-00000344": {"category": "Drug", "address": "600 30TH ST Boulder CO", "date": "02/03/2018 00:19 - 02/03/2018 00:37"}}
{"2018-00000348": {"category": "Alcohol", "address": "600 30TH ST Boulder CO", "date": "02/03/2018 01:20 - 02/03/2018 01:20"}}
{"2018-00000349": {"category": "Criminal", "address": "USHY 36 /  BASELINE RD Boulder CO", "date": "02/03/2018 01:20 - 02/03/2018 02:00"}}
{"2018-00000350": {"category": "Criminal", "address": "1669 EUCLID AVE Boulder CO", "date": "02/03/2018 01:05 - 02/03/2018 01:05"}}
{"2018-00000351": {"category": "Alcohol", "address": "2590 KITTREDGE LOOP DR Boulder CO", "date": "02/03/2018 01:23 - 02/03/2018 01:23"}}
{"2018-00000353": {"category": "DUI/DWAI", "address": "1040 REGENT DR Boulder CO", "date": "02/03/2018 03:09 - 02/03/2018 03:09"}}
{"2018-00000353": {"category": "DUI/DWAI", "address": "1040 REGENT DR Boulder CO", "date": "02/03/2018 03:09 - 02/03/2018 03:09"}}
{"2018-00000353": {"category": "DUI/DWAI", "address": "1040 REGENT DR Boulder CO", "date": "02/03/2018 03:09 - 02/03/2018 03:09"}}
{"2018-00000357": {"category": "Alcohol", "address": "960 GREEN MOUNTAIN DR Boulder CO", "date": "02/03/2018 21:50 - 02/03/2018 22:14"}}
{"2018-00008086": {"category": "Theft", "address": "960 GREEN MOUNTAIN DR Boulder CO", "date": "02/02/2018 10:00 - 02/03/2018 06:15"}}
{"2018-00008087": {"category": "Theft", "address": "2370 LIBBY DR Boulder CO", "date": "01/28/2018 12:20 - 01/28/2018 12:20"}}
{"2018-00000237": {"category": "Alcohol", "address": "1595 PLEASANT ST Boulder CO", "date": "01/26/2018 00:19 - 01/26/2018 00:19"}}
{"2018-00000237": {"category": "Alcohol", "address": "1595 PLEASANT ST Boulder CO", "date": "01/26/2018 00:19 - 01/26/2018 00:19"}}
{"2018-00000239": {"category": "Drug", "address": "2005 BAKER DR Boulder CO", "date": "01/26/2018 00:54 - 01/26/2018 01:27"}}
{"2018-00000239": {"category": "Drug", "address": "2005 BAKER DR Boulder CO", "date": "01/26/2018 00:54 - 01/26/2018 01:27"}}
{"2018-00000239": {"category": "Drug", "address": "2005 BAKER DR Boulder CO", "date": "01/26/2018 00:54 - 01/26/2018 01:27"}}
{"2018-00000239": {"category": "Drug", "address": "2005 BAKER DR Boulder CO", "date": "01/26/2018 00:54 - 01/26/2018 01:27"}}
{"2018-00000240": {"category": "DUI/DWAI", "address": "ARAPAHOE AVE /  FOLSOM Boulder CO", "date": "01/26/2018 00:55 - 01/26/2018 00:55"}}
{"2018-00000240": {"category": "DUI/DWAI", "address": "ARAPAHOE AVE /  FOLSOM Boulder CO", "date": "01/26/2018 00:55 - 01/26/2018 00:55"}}
{"2018-00000240": {"category": "DUI/DWAI", "address": "ARAPAHOE AVE /  FOLSOM Boulder CO", "date": "01/26/2018 00:55 - 01/26/2018 00:55"}}
{"2018-00000240": {"category": "DUI/DWAI", "address": "ARAPAHOE AVE /  FOLSOM Boulder CO", "date": "01/26/2018 00:55 - 01/26/2018 00:55"}}
{"2018-00000240": {"category": "DUI/DWAI", "address": "ARAPAHOE AVE /  FOLSOM Boulder CO", "date": "01/26/2018 00:55 - 01/26/2018 00:55"}}
{"2018-00000241": {"category": "Drug", "address": "3300 BASELINE RD Boulder CO", "date": "01/26/2018 01:41 - 01/26/2018 01:41"}}
{"2018-00000241": {"category": "Drug", "address": "3300 BASELINE RD Boulder CO", "date": "01/26/2018 01:41 - 01/26/2018 01:41"}}
{"2018-00000242": {"category": "Drug", "address": "27TH WAY /  BASELINE RD Boulder CO", "date": "01/26/2018 03:58 - 01/26/2018 03:58"}}
{"2018-00000242": {"category": "Drug", "address": "27TH WAY /  BASELINE RD Boulder CO", "date": "01/26/2018 03:58 - 01/26/2018 03:58"}}
{"2018-00000242": {"category": "Drug", "address": "27TH WAY /  BASELINE RD Boulder CO", "date": "01/26/2018 03:58 - 01/26/2018 03:58"}}
{"2018-00000242": {"category": "Drug", "address": "27TH WAY /  BASELINE RD Boulder CO", "date": "01/26/2018 03:58 - 01/26/2018 03:58"}}
{"2018-00000244": {"category": "Traffic", "address": "1995 COLORADO AVE Boulder CO", "date": "01/17/2018 06:20 - 01/17/2018 06:20"}}
{"2018-00000247": {"category": "Violation", "address": "3415 COLORADO AVE Boulder CO", "date": "01/26/2018 00:30 - 01/26/2018 00:30"}}
{"2018-00000247": {"category": "Violation", "address": "3415 COLORADO AVE Boulder CO", "date": "01/26/2018 00:30 - 01/26/2018 00:30"}}
{"2018-00000250": {"category": "Other", "address": "3355 APACHE RD Boulder CO", "date": "01/26/2018 22:30 - 01/26/2018 22:30"}}
{"2018-00008052": {"category": "Theft", "address": "3300 BASELINE RD Boulder CO", "date": "01/25/2018 18:30 - 01/26/2018 10:30"}}
{"2018-00000407": {"category": "Traffic", "address": "2005 BAKER DR Boulder CO", "date": "02/08/2018 14:10 - 02/08/2018 14:10"}}
{"2018-00000407": {"category": "Traffic", "address": "2005 BAKER DR Boulder CO", "date": "02/08/2018 14:10 - 02/08/2018 14:10"}}
{"2018-00000417": {"category": "Alcohol", "address": "2200 WILLARD LOOP DR Boulder CO", "date": "02/09/2018 00:40 - 02/09/2018 00:40"}}
{"2018-00000419": {"category": "Alcohol", "address": "2200 BAKER DR Boulder CO", "date": "02/09/2018 01:18 - 02/09/2018 02:26"}}
{"2018-00000420": {"category": "Alcohol", "address": "550 30TH ST Boulder CO", "date": "02/09/2018 02:20 - 02/09/2018 02:20"}}
{"2018-00000421": {"category": "Accident", "address": "1050 REGENT DR Boulder CO", "date": "02/09/2018 10:21 - 02/09/2018 10:21"}}
{"2018-00000422": {"category": "Warrant", "address": "1234 INNOVATION DR Boulder CO", "date": "02/09/2018 09:49 - 02/09/2018 10:40"}}
{"2018-00000422": {"category": "Warrant", "address": "1234 INNOVATION DR Boulder CO", "date": "02/09/2018 09:49 - 02/09/2018 10:40"}}
{"2018-00000423": {"category": "Traffic", "address": "1075 REGENT DR Boulder CO", "date": "02/09/2018 08:25 - 02/09/2018 08:25"}}
{"2018-00000423": {"category": "Traffic", "address": "1075 REGENT DR Boulder CO", "date": "02/09/2018 08:25 - 02/09/2018 08:25"}}
{"2018-00000425": {"category": "Property", "address": "1050 REGENT DR Boulder CO", "date": "02/09/2018 14:15 - 02/09/2018 14:15"}}
{"2018-00000430": {"category": "Drug", "address": "500 30TH ST Boulder CO", "date": "02/09/2018 18:51 - 02/09/2018 18:51"}}
{"2018-00000430": {"category": "Drug", "address": "500 30TH ST Boulder CO", "date": "02/09/2018 18:51 - 02/09/2018 18:51"}}
{"2018-00000431": {"category": "Traffic", "address": "REGENT DR /  KITTREDGE Boulder CO", "date": "02/09/2018 18:46 - 02/09/2018 18:46"}}
{"2018-00000432": {"category": "Drug", "address": "500 30TH ST Boulder CO", "date": "02/09/2018 19:55 - 02/09/2018 20:05"}}
{"2018-00000433": {"category": "Alcohol", "address": "2200 BAKER DR Boulder CO", "date": "02/09/2018 20:56 - 02/09/2018 21:11"}}
{"2018-00000436": {"category": "Alcohol", "address": "2480 KITTREDGE LOOP DR Boulder CO", "date": "02/09/2018 21:45 - 02/10/2018 02:30"}}
{"2018-00000437": {"category": "Alcohol", "address": "2115 BAKER DR Boulder CO", "date": "02/09/2018 22:22 - 02/09/2018 22:34"}}
{"2018-00000438": {"category": "Drug", "address": "2249 WILLARD LOOP DR Boulder CO", "date": "02/09/2018 22:29 - 02/09/2018 22:29"}}
{"2018-00000438": {"category": "Drug", "address": "2249 WILLARD LOOP DR Boulder CO", "date": "02/09/2018 22:29 - 02/09/2018 22:29"}}
{"2018-00000439": {"category": "Warrant", "address": "1669 EUCLID AVE Boulder CO", "date": "02/09/2018 22:19 - 02/10/2018 00:09"}}
{"2018-00000440": {"category": "Drug", "address": "2200 WILLARD LOOP DR Boulder CO", "date": "02/09/2018 22:47 - 02/09/2018 23:45"}}
{"2018-00000440": {"category": "Drug", "address": "2200 WILLARD LOOP DR Boulder CO", "date": "02/09/2018 22:47 - 02/09/2018 23:45"}}
{"2018-00000662": {"category": "DUI/DWAI", "address": "USHY 36 /  TABLE MESA DR Boulder CO", "date": "02/24/2018 22:45 - 02/25/2018 01:51"}}
{"2018-00000662": {"category": "DUI/DWAI", "address": "USHY 36 /  TABLE MESA DR Boulder CO", "date": "02/24/2018 22:45 - 02/25/2018 01:51"}}
{"2018-00000662": {"category": "DUI/DWAI", "address": "USHY 36 /  TABLE MESA DR Boulder CO", "date": "02/24/2018 22:45 - 02/25/2018 01:51"}}
{"2018-00000662": {"category": "DUI/DWAI", "address": "USHY 36 /  TABLE MESA DR Boulder CO", "date": "02/24/2018 22:45 - 02/25/2018 01:51"}}
{"2018-00000664": {"category": "Criminal", "address": "3400 BASELINE RD Boulder CO", "date": "02/25/2018 00:42 - 02/25/2018 00:42"}}
{"2018-00000665": {"category": "Other", "address": "2000 BAKER DR Boulder CO", "date": "02/25/2018 01:44 - 02/25/2018 01:44"}}
{"2018-00000667": {"category": "Other", "address": "2200 WILLARD LOOP DR Boulder CO", "date": "02/25/2018 03:00 - 02/25/2018 03:00"}}
{"2018-00000667": {"category": "Other", "address": "2200 WILLARD LOOP DR Boulder CO", "date": "02/25/2018 03:00 - 02/25/2018 03:00"}}
{"2018-00000667": {"category": "Other", "address": "2200 WILLARD LOOP DR Boulder CO", "date": "02/25/2018 03:00 - 02/25/2018 03:00"}}
{"2018-00000668": {"category": "Criminal", "address": "2250 WILLARD LOOP DR Boulder CO", "date": "02/25/2018 01:45 - 02/25/2018 01:45"}}
{"2018-00000669": {"category": "Traffic", "address": "1725 EUCLID AVE Boulder CO", "date": "02/25/2018 13:00 - 02/25/2018 15:43"}}
{"2018-00000669": {"category": "Traffic", "address": "1725 EUCLID AVE Boulder CO", "date": "02/25/2018 13:00 - 02/25/2018 15:43"}}
{"2018-00000670": {"category": "Fraud/Forgery", "address": "2200 WILLARD LOOP DR Boulder CO", "date": "02/25/2018 19:35 - 02/25/2018 19:53"}}
{"2018-00000670": {"category": "Fraud/Forgery", "address": "2200 WILLARD LOOP DR Boulder CO", "date": "02/25/2018 19:35 - 02/25/2018 19:53"}}
{"2018-00000670": {"category": "Fraud/Forgery", "address": "2200 WILLARD LOOP DR Boulder CO", "date": "02/25/2018 19:35 - 02/25/2018 19:53"}}
{"2018-00000670": {"category": "Fraud/Forgery", "address": "2200 WILLARD LOOP DR Boulder CO", "date": "02/25/2018 19:35 - 02/25/2018 19:53"}}
{"2018-00000671": {"category": "Alcohol", "address": "2115 BAKER DR Boulder CO", "date": "02/25/2018 20:32 - 02/25/2018 20:38"}}
{"2018-00000672": {"category": "Theft", "address": "2005 BAKER DR Boulder CO", "date": "02/25/2018 21:11 - 02/25/2018 21:11"}}
{"2018-00000673": {"category": "Drug", "address": "960 GREEN MOUNTAIN DR Boulder CO", "date": "02/25/2018 21:48 - 02/25/2018 22:02"}}
{"2018-00000674": {"category": "Drug", "address": "2200 WILLARD LOOP DR Boulder CO", "date": "02/25/2018 22:24 - 02/25/2018 22:53"}}
{"2018-00000674": {"category": "Drug", "address": "2200 WILLARD LOOP DR Boulder CO", "date": "02/25/2018 22:24 - 02/25/2018 22:53"}}
{"2018-00000674": {"category": "Drug", "address": "2200 WILLARD LOOP DR Boulder CO", "date": "02/25/2018 22:24 - 02/25/2018 22:53"}}
{"2018-00000100": {"category": "Theft", "address": "1669 EUCLID AVE Boulder CO", "date": "01/17/2018 13:45 - 01/17/2018 13:45"}}
{"2018-00000210": {"category": "Criminal", "address": "960 GREEN MOUNTAIN DR Boulder CO", "date": "01/23/2018 20:00 - 01/23/2018 22:30"}}
{"2018-00000215": {"category": "Criminal", "address": "1300 30TH ST Boulder CO", "date": "01/24/2018 04:45 - 01/24/2018 10:00"}}
{"2018-00000215": {"category": "Criminal", "address": "1300 30TH ST Boulder CO", "date": "01/24/2018 04:45 - 01/24/2018 10:00"}}
{"2018-00000217": {"category": "Criminal", "address": "4001 DISCOVERY DR Boulder CO", "date": "01/24/2018 00:30 - 01/24/2018 07:00"}}
{"2018-00000217": {"category": "Criminal", "address": "4001 DISCOVERY DR Boulder CO", "date": "01/24/2018 00:30 - 01/24/2018 07:00"}}
{"2018-00000220": {"category": "Traffic", "address": "1050 REGENT DR Boulder CO", "date": "01/24/2018 13:42 - 01/24/2018 13:42"}}
{"2018-00000222": {"category": "Theft", "address": "3415 COLORADO AVE Boulder CO", "date": "01/24/2018 16:30 - 01/24/2018 16:30"}}
{"2018-00000224": {"category": "Drug", "address": "500 30TH ST Boulder CO", "date": "01/24/2018 21:33 - 01/24/2018 22:05"}}
{"2018-00000224": {"category": "Drug", "address": "500 30TH ST Boulder CO", "date": "01/24/2018 21:33 - 01/24/2018 22:05"}}
{"2018-00008049": {"category": "Theft", "address": "2480 KITTREDGE LOOP DR Boulder CO", "date": "01/23/2018 17:50 - 01/24/2018 11:00"}}
{"2018-00000487": {"category": "Damage", "address": "1050 REGENT DR Boulder CO", "date": "02/08/2018 13:30 - 02/13/2018 14:14"}}
{"2018-00000488": {"category": "Other", "address": "2450 KITTREDGE LOOP DR Boulder CO", "date": "02/13/2018 14:45 - 02/13/2018 14:45"}}
{"2018-00000491": {"category": "Drug", "address": "2200 BAKER DR Boulder CO", "date": "02/13/2018 20:52 - 02/13/2018 21:03"}}
{"2018-00000492": {"category": "Alcohol", "address": "2200 BAKER DR Boulder CO", "date": "02/13/2018 21:07 - 02/13/2018 21:25"}}
{"2018-00000505": {"category": "DUI/DWAI", "address": "BROADWAY /  16TH ST Boulder CO", "date": "02/14/2018 23:43 - 02/14/2018 23:43"}}
{"2018-00000505": {"category": "DUI/DWAI", "address": "BROADWAY /  16TH ST Boulder CO", "date": "02/14/2018 23:43 - 02/14/2018 23:43"}}
{"2018-00000505": {"category": "DUI/DWAI", "address": "BROADWAY /  16TH ST Boulder CO", "date": "02/14/2018 23:43 - 02/14/2018 23:43"}}
{"2018-00000505": {"category": "DUI/DWAI", "address": "BROADWAY /  16TH ST Boulder CO", "date": "02/14/2018 23:43 - 02/14/2018 23:43"}}
{"2018-00000505": {"category": "DUI/DWAI", "address": "BROADWAY /  16TH ST Boulder CO", "date": "02/14/2018 23:43 - 02/14/2018 23:43"}}
{"2018-00000505": {"category": "DUI/DWAI", "address": "BROADWAY /  16TH ST Boulder CO", "date": "02/14/2018 23:43 - 02/14/2018 23:43"}}
{"2018-00000505": {"category": "DUI/DWAI", "address": "BROADWAY /  16TH ST Boulder CO", "date": "02/14/2018 23:43 - 02/14/2018 23:43"}}
{"2018-00000506": {"category": "Alcohol", "address": "2005 BAKER DR Boulder CO", "date": "02/15/2018 00:10 - 02/15/2018 00:10"}}
{"2018-00000506": {"category": "Alcohol", "address": "2005 BAKER DR Boulder CO", "date": "02/15/2018 00:10 - 02/15/2018 00:10"}}
{"2018-00000508": {"category": "Criminal", "address": "3400 BASELINE RD Boulder CO", "date": "02/15/2018 01:02 - 02/15/2018 01:20"}}
{"2018-00000509": {"category": "Other", "address": "18TH ST /  COLORADO AVE Boulder CO", "date": "02/15/2018 02:29 - 02/15/2018 02:29"}}
{"2018-00000509": {"category": "Other", "address": "18TH ST /  COLORADO AVE Boulder CO", "date": "02/15/2018 02:29 - 02/15/2018 02:29"}}
{"2018-00000510": {"category": "DUI/DWAI", "address": "30TH ST /  BASELINE RD Boulder CO", "date": "02/15/2018 02:40 - 02/15/2018 02:40"}}
{"2018-00000510": {"category": "DUI/DWAI", "address": "30TH ST /  BASELINE RD Boulder CO", "date": "02/15/2018 02:40 - 02/15/2018 02:40"}}
{"2018-00000510": {"category": "DUI/DWAI", "address": "30TH ST /  BASELINE RD Boulder CO", "date": "02/15/2018 02:40 - 02/15/2018 02:40"}}
{"2018-00000510": {"category": "DUI/DWAI", "address": "30TH ST /  BASELINE RD Boulder CO", "date": "02/15/2018 02:40 - 02/15/2018 02:40"}}
{"2018-00000510": {"category": "DUI/DWAI", "address": "30TH ST /  BASELINE RD Boulder CO", "date": "02/15/2018 02:40 - 02/15/2018 02:40"}}
{"2018-00000510": {"category": "DUI/DWAI", "address": "30TH ST /  BASELINE RD Boulder CO", "date": "02/15/2018 02:40 - 02/15/2018 02:40"}}
{"2018-00000512": {"category": "Drug", "address": "960 GREEN MOUNTAIN DR Boulder CO", "date": "02/15/2018 08:02 - 02/15/2018 08:02"}}
{"2018-00000512": {"category": "Drug", "address": "960 GREEN MOUNTAIN DR Boulder CO", "date": "02/15/2018 08:02 - 02/15/2018 08:02"}}
{"2018-00000517": {"category": "Criminal", "address": "2249 WILLARD LOOP DR Boulder CO", "date": "02/15/2018 15:30 - 02/15/2018 15:30"}}
{"2018-00000518": {"category": "Other", "address": "2300 COLORADO AVE Boulder CO", "date": "02/15/2018 17:00 - 02/15/2018 17:00"}}
{"2018-00000518": {"category": "Other", "address": "2300 COLORADO AVE Boulder CO", "date": "02/15/2018 17:00 - 02/15/2018 17:00"}}
{"2018-00000520": {"category": "Alcohol", "address": "2480 KITTREDGE LOOP DR Boulder CO", "date": "02/15/2018 19:33 - 02/15/2018 19:33"}}
{"2018-00000522": {"category": "Drug", "address": "500 30TH ST Boulder CO", "date": "02/15/2018 22:00 - 02/15/2018 22:00"}}
{"2018-00000522": {"category": "Drug", "address": "500 30TH ST Boulder CO", "date": "02/15/2018 22:00 - 02/15/2018 22:00"}}
{"2018-00000522": {"category": "Drug", "address": "500 30TH ST Boulder CO", "date": "02/15/2018 22:00 - 02/15/2018 22:00"}}
{"2018-00000524": {"category": "Drug", "address": "960 GREEN MOUNTAIN DR Boulder CO", "date": "02/15/2018 23:02 - 02/16/2018 00:06"}}
{"2018-00000524": {"category": "Drug", "address": "960 GREEN MOUNTAIN DR Boulder CO", "date": "02/15/2018 23:02 - 02/16/2018 00:06"}}
{"2018-00000524": {"category": "Drug", "address": "960 GREEN MOUNTAIN DR Boulder CO", "date": "02/15/2018 23:02 - 02/16/2018 00:06"}}
{"2018-00008122": {"category": "Theft", "address": "1669 EUCLID AVE Boulder CO", "date": "02/15/2018 08:05 - 02/15/2018 17:15"}}
{"2018-00000144": {"category": "Other", "address": "2200 BAKER DR Boulder CO", "date": "01/20/2018 00:36 - 01/20/2018 01:19"}}
{"2018-00000144": {"category": "Other", "address": "2200 BAKER DR Boulder CO", "date": "01/20/2018 00:36 - 01/20/2018 01:19"}}
{"2018-00000144": {"category": "Other", "address": "2200 BAKER DR Boulder CO", "date": "01/20/2018 00:36 - 01/20/2018 01:19"}}
{"2018-00000309": {"category": "Drug", "address": "2115 BAKER DR Boulder CO", "date": "02/01/2018 11:00 - 02/01/2018 11:00"}}
{"2018-00000312": {"category": "Burglary", "address": "1720 UNIVERSITY AVE Boulder CO", "date": "02/01/2018 14:00 - 02/01/2018 16:00"}}
{"2018-00000312": {"category": "Burglary", "address": "1720 UNIVERSITY AVE Boulder CO", "date": "02/01/2018 14:00 - 02/01/2018 16:00"}}
{"2018-00000313": {"category": "Traffic", "address": "1020 BROADWAY Boulder CO", "date": "02/01/2018 17:20 - 02/01/2018 22:07"}}
{"2018-00000315": {"category": "Drug", "address": "1720 UNIVERSITY AVE Boulder CO", "date": "02/01/2018 17:54 - 02/01/2018 17:54"}}
{"2018-00000316": {"category": "Drug", "address": "2200 BAKER DR Boulder CO", "date": "02/01/2018 20:30 - 02/01/2018 20:30"}}
{"2018-00000316": {"category": "Drug", "address": "2200 BAKER DR Boulder CO", "date": "02/01/2018 20:30 - 02/01/2018 20:30"}}
{"2018-00000318": {"category": "Drug", "address": "2200 WILLARD LOOP DR Boulder CO", "date": "02/01/2018 22:10 - 02/01/2018 22:10"}}
{"2018-00000318": {"category": "Drug", "address": "2200 WILLARD LOOP DR Boulder CO", "date": "02/01/2018 22:10 - 02/01/2018 22:10"}}
{"2018-00000319": {"category": "Alcohol", "address": "500 30TH ST Boulder CO", "date": "02/01/2018 21:54 - 02/01/2018 22:26"}}
{"2018-00000319": {"category": "Alcohol", "address": "500 30TH ST Boulder CO", "date": "02/01/2018 21:54 - 02/01/2018 22:26"}}
{"2018-00000263": {"category": "Theft", "address": "3645 MARINE ST Boulder CO", "date": "01/27/2018 21:55 - 01/27/2018 21:55"}}
{"2018-00000266": {"category": "Warrant", "address": "3625 DISCOVERY DR Boulder CO", "date": "01/27/2018 22:50 - 01/27/2018 22:50"}}
{"2018-00000267": {"category": "Criminal", "address": "3275 APACHE RD Boulder CO", "date": "01/27/2018 23:41 - 01/27/2018 23:41"}}
{"2018-00000268": {"category": "Drug", "address": "3625 DISCOVERY DR Boulder CO", "date": "01/27/2018 22:50 - 01/27/2018 22:50"}}
{"2018-00000268": {"category": "Drug", "address": "3625 DISCOVERY DR Boulder CO", "date": "01/27/2018 22:50 - 01/27/2018 22:50"}}
{"2018-00000268": {"category": "Drug", "address": "3625 DISCOVERY DR Boulder CO", "date": "01/27/2018 22:50 - 01/27/2018 22:50"}}
{"2018-00000268": {"category": "Drug", "address": "3625 DISCOVERY DR Boulder CO", "date": "01/27/2018 22:50 - 01/27/2018 22:50"}}
{"2018-00000270": {"category": "Drug", "address": "2115 BAKER DR Boulder CO", "date": "01/28/2018 01:40 - 01/28/2018 02:04"}}
{"2018-00000270": {"category": "Drug", "address": "2115 BAKER DR Boulder CO", "date": "01/28/2018 01:40 - 01/28/2018 02:04"}}
{"2018-00000271": {"category": "Assault", "address": "960 GREEN MOUNTAIN DR Boulder CO", "date": "01/28/2018 04:25 - 01/28/2018 05:00"}}
{"2018-00000271": {"category": "Assault", "address": "960 GREEN MOUNTAIN DR Boulder CO", "date": "01/28/2018 04:25 - 01/28/2018 05:00"}}
{"2018-00000271": {"category": "Assault", "address": "960 GREEN MOUNTAIN DR Boulder CO", "date": "01/28/2018 04:25 - 01/28/2018 05:00"}}
{"2018-00000272": {"category": "Alcohol", "address": "2005 BAKER DR Boulder CO", "date": "01/28/2018 20:56 - 01/28/2018 21:07"}}
{"2018-00000273": {"category": "Drug", "address": "2250 WILLARD LOOP DR Boulder CO", "date": "01/28/2018 21:45 - 01/28/2018 21:45"}}
{"2018-00000273": {"category": "Drug", "address": "2250 WILLARD LOOP DR Boulder CO", "date": "01/28/2018 21:45 - 01/28/2018 21:45"}}
{"2018-00000273": {"category": "Drug", "address": "2250 WILLARD LOOP DR Boulder CO", "date": "01/28/2018 21:45 - 01/28/2018 21:45"}}
{"2018-00000274": {"category": "Alcohol", "address": "3300 BASELINE RD Boulder CO", "date": "01/28/2018 22:10 - 01/28/2018 22:30"}}
{"2018-00008057": {"category": "Theft", "address": "1910 ATHENS ST Boulder CO", "date": "01/28/2018 02:00 - 01/28/2018 07:00"}}
{"2018-00008058": {"category": "Theft", "address": "2115 BAKER DR Boulder CO", "date": "01/26/2018 22:05 - 01/26/2018 22:05"}}
{"2018-00008058": {"category": "Theft", "address": "2115 BAKER DR Boulder CO", "date": "01/26/2018 22:05 - 01/26/2018 22:05"}}
{"2018-00000778": {"category": "DUI/DWAI", "address": "BROADWAY /  EUCLID AVE Boulder CO", "date": "03/05/2018 23:42 - 03/05/2018 23:42"}}
{"2018-00000778": {"category": "DUI/DWAI", "address": "BROADWAY /  EUCLID AVE Boulder CO", "date": "03/05/2018 23:42 - 03/05/2018 23:42"}}
{"2018-00000782": {"category": "Traffic", "address": "1050 REGENT DR Boulder CO", "date": "03/06/2018 10:30 - 03/06/2018 10:30"}}
{"2018-00000782": {"category": "Traffic", "address": "1050 REGENT DR Boulder CO", "date": "03/06/2018 10:30 - 03/06/2018 10:30"}}
{"2018-00000782": {"category": "Traffic", "address": "1050 REGENT DR Boulder CO", "date": "03/06/2018 10:30 - 03/06/2018 10:30"}}
{"2018-00000782": {"category": "Traffic", "address": "1050 REGENT DR Boulder CO", "date": "03/06/2018 10:30 - 03/06/2018 10:30"}}
{"2018-00000782": {"category": "Traffic", "address": "1050 REGENT DR Boulder CO", "date": "03/06/2018 10:30 - 03/06/2018 10:30"}}
{"2018-00000785": {"category": "Sex", "address": "3275 APACHE RD Boulder CO", "date": "03/04/2018 01:00 - 03/04/2018 08:00"}}
{"2018-00000786": {"category": "Criminal", "address": "2570 KITTREDGE LOOP DR Boulder CO", "date": "03/02/2018 22:00 - 03/06/2018 18:17"}}
{"2018-00000788": {"category": "Drug", "address": "3300 BASELINE RD Boulder CO", "date": "03/06/2018 23:50 - 03/06/2018 23:50"}}
{"2018-00000788": {"category": "Drug", "address": "3300 BASELINE RD Boulder CO", "date": "03/06/2018 23:50 - 03/06/2018 23:50"}}
{"2018-00008160": {"category": "Theft", "address": "1720 PLEASANT ST Boulder CO", "date": "03/06/2018 13:50 - 03/06/2018 14:00"}}
{"2018-00008162": {"category": "Theft", "address": "2200 WILLARD LOOP DR Boulder CO", "date": "03/06/2018 20:20 - 03/06/2018 20:20"}}
{"2018-00000303": {"category": "Drug", "address": "1001 COCKERELL DR Boulder CO", "date": "01/31/2018 16:40 - 01/31/2018 17:19"}}
{"2018-00000303": {"category": "Drug", "address": "1001 COCKERELL DR Boulder CO", "date": "01/31/2018 16:40 - 01/31/2018 17:19"}}
{"2018-00000305": {"category": "Drug", "address": "2480 KITTREDGE LOOP DR Boulder CO", "date": "01/31/2018 20:56 - 01/31/2018 21:50"}}
{"2018-00000305": {"category": "Drug", "address": "2480 KITTREDGE LOOP DR Boulder CO", "date": "01/31/2018 20:56 - 01/31/2018 21:50"}}
{"2018-00008074": {"category": "Criminal", "address": "2085 COLORADO AVE Boulder CO", "date": "01/31/2018 06:00 - 01/31/2018 06:00"}}
{"2018-00000402": {"category": "Drug", "address": "1720 UNIVERSITY AVE Boulder CO", "date": "02/08/2018 00:56 - 02/08/2018 01:09"}}
{"2018-00000403": {"category": "Theft", "address": "2525 KITTREDGE LOOP DR Boulder CO", "date": "02/08/2018 03:44 - 02/08/2018 03:47"}}
{"2018-00000403": {"category": "Theft", "address": "2525 KITTREDGE LOOP DR Boulder CO", "date": "02/08/2018 03:44 - 02/08/2018 03:47"}}
{"2018-00000405": {"category": "Traffic", "address": "1050 REGENT DR Boulder CO", "date": "02/08/2018 10:39 - 02/08/2018 10:39"}}
{"2018-00000407": {"category": "Traffic", "address": "2005 BAKER DR Boulder CO", "date": "02/08/2018 14:10 - 02/08/2018 14:10"}}
{"2018-00000407": {"category": "Traffic", "address": "2005 BAKER DR Boulder CO", "date": "02/08/2018 14:10 - 02/08/2018 14:10"}}
{"2018-00000408": {"category": "Other", "address": "3300 BASELINE RD Boulder CO", "date": "02/07/2018 14:00 - 02/08/2018 15:00"}}
{"2018-00000408": {"category": "Other", "address": "3300 BASELINE RD Boulder CO", "date": "02/07/2018 14:00 - 02/08/2018 15:00"}}
{"2018-00000410": {"category": "Traffic", "address": "2291 LIBBY DR Boulder CO", "date": "02/08/2018 14:00 - 02/08/2018 14:00"}}
{"2018-00000411": {"category": "Alcohol", "address": "2200 WILLARD LOOP DR Boulder CO", "date": "02/08/2018 20:15 - 02/08/2018 20:15"}}
{"2018-00000412": {"category": "Criminal", "address": "3300 BASELINE RD Boulder CO", "date": "02/05/2018 10:00 - 02/08/2018 21:00"}}
{"2018-00000414": {"category": "Alcohol", "address": "2005 BAKER DR Boulder CO", "date": "02/08/2018 21:56 - 02/08/2018 22:12"}}
{"2018-00000416": {"category": "Alcohol", "address": "2115 BAKER DR Boulder CO", "date": "02/08/2018 22:38 - 02/08/2018 23:01"}}
{"2018-00000763": {"category": "Other", "address": "3355 APACHE RD Boulder CO", "date": "03/04/2018 22:19 - 03/04/2018 22:19"}}
{"2018-00000763": {"category": "Other", "address": "3355 APACHE RD Boulder CO", "date": "03/04/2018 22:19 - 03/04/2018 22:19"}}
{"2018-00000765": {"category": "Traffic", "address": "18TH ST /  EUCLID AVE Boulder CO", "date": "03/05/2018 00:01 - 03/05/2018 02:03"}}
{"2018-00000765": {"category": "Traffic", "address": "18TH ST /  EUCLID AVE Boulder CO", "date": "03/05/2018 00:01 - 03/05/2018 02:03"}}
{"2018-00000765": {"category": "Traffic", "address": "18TH ST /  EUCLID AVE Boulder CO", "date": "03/05/2018 00:01 - 03/05/2018 02:03"}}
{"2018-00000765": {"category": "Traffic", "address": "18TH ST /  EUCLID AVE Boulder CO", "date": "03/05/2018 00:01 - 03/05/2018 02:03"}}
{"2018-00000766": {"category": "Drug", "address": "1720 UNIVERSITY AVE Boulder CO", "date": "03/05/2018 01:04 - 03/05/2018 01:18"}}
{"2018-00000767": {"category": "Criminal", "address": "1157 18TH ST Boulder CO", "date": "03/05/2018 07:52 - 03/05/2018 07:52"}}
{"2018-00000768": {"category": "Drug", "address": "960 GREEN MOUNTAIN DR Boulder CO", "date": "03/05/2018 09:33 - 03/05/2018 09:33"}}
{"2018-00000772": {"category": "Criminal", "address": "3275 APACHE RD Boulder CO", "date": "03/05/2018 13:00 - 03/05/2018 13:00"}}
{"2018-00000775": {"category": "Harassment", "address": "1050 REGENT DR Boulder CO", "date": "03/05/2018 16:53 - 03/05/2018 16:53"}}
{"2018-00000776": {"category": "Drug", "address": "1720 UNIVERSITY AVE Boulder CO", "date": "03/05/2018 21:02 - 03/05/2018 21:53"}}
{"2018-00000776": {"category": "Drug", "address": "1720 UNIVERSITY AVE Boulder CO", "date": "03/05/2018 21:02 - 03/05/2018 21:53"}}
{"2018-00000776": {"category": "Drug", "address": "1720 UNIVERSITY AVE Boulder CO", "date": "03/05/2018 21:02 - 03/05/2018 21:53"}}
{"2018-00000778": {"category": "DUI/DWAI", "address": "BROADWAY /  EUCLID AVE Boulder CO", "date": "03/05/2018 23:42 - 03/05/2018 23:42"}}
{"2018-00000778": {"category": "DUI/DWAI", "address": "BROADWAY /  EUCLID AVE Boulder CO", "date": "03/05/2018 23:42 - 03/05/2018 23:42"}}
{"2018-00000779": {"category": "Alcohol", "address": "600 30TH ST Boulder CO", "date": "03/05/2018 23:51 - 03/06/2018 00:13"}}
{"2018-00000493": {"category": "Drug", "address": "1720 UNIVERSITY AVE Boulder CO", "date": "02/14/2018 00:40 - 02/14/2018 01:17"}}
{"2018-00000493": {"category": "Drug", "address": "1720 UNIVERSITY AVE Boulder CO", "date": "02/14/2018 00:40 - 02/14/2018 01:17"}}
{"2018-00000494": {"category": "Traffic", "address": "1669 EUCLID AVE Boulder CO", "date": "02/14/2018 08:45 - 02/14/2018 10:00"}}
{"2018-00000499": {"category": "Accident", "address": "2291 LIBBY DR Boulder CO", "date": "02/14/2018 18:00 - 02/14/2018 18:00"}}
{"2018-00000501": {"category": "Drug", "address": "2590 KITTREDGE LOOP DR Boulder CO", "date": "02/14/2018 21:30 - 02/14/2018 21:30"}}
{"2018-00000501": {"category": "Drug", "address": "2590 KITTREDGE LOOP DR Boulder CO", "date": "02/14/2018 21:30 - 02/14/2018 21:30"}}
{"2018-00000503": {"category": "Drug", "address": "600 30TH ST Boulder CO", "date": "02/14/2018 23:20 - 02/14/2018 23:20"}}
{"2018-00000503": {"category": "Drug", "address": "600 30TH ST Boulder CO", "date": "02/14/2018 23:20 - 02/14/2018 23:20"}}
{"2018-00000505": {"category": "DUI/DWAI", "address": "BROADWAY /  16TH ST Boulder CO", "date": "02/14/2018 23:43 - 02/14/2018 23:43"}}
{"2018-00000505": {"category": "DUI/DWAI", "address": "BROADWAY /  16TH ST Boulder CO", "date": "02/14/2018 23:43 - 02/14/2018 23:43"}}
{"2018-00000505": {"category": "DUI/DWAI", "address": "BROADWAY /  16TH ST Boulder CO", "date": "02/14/2018 23:43 - 02/14/2018 23:43"}}
{"2018-00000505": {"category": "DUI/DWAI", "address": "BROADWAY /  16TH ST Boulder CO", "date": "02/14/2018 23:43 - 02/14/2018 23:43"}}
{"2018-00000505": {"category": "DUI/DWAI", "address": "BROADWAY /  16TH ST Boulder CO", "date": "02/14/2018 23:43 - 02/14/2018 23:43"}}
{"2018-00000505": {"category": "DUI/DWAI", "address": "BROADWAY /  16TH ST Boulder CO", "date": "02/14/2018 23:43 - 02/14/2018 23:43"}}
{"2018-00000505": {"category": "DUI/DWAI", "address": "BROADWAY /  16TH ST Boulder CO", "date": "02/14/2018 23:43 - 02/14/2018 23:43"}}
{"2018-00000436": {"category": "Alcohol", "address": "2480 KITTREDGE LOOP DR Boulder CO", "date": "02/09/2018 21:45 - 02/10/2018 02:30"}}
{"2018-00000439": {"category": "Warrant", "address": "1669 EUCLID AVE Boulder CO", "date": "02/09/2018 22:19 - 02/10/2018 00:09"}}
{"2018-00000441": {"category": "Alcohol", "address": "2250 WILLARD LOOP DR Boulder CO", "date": "02/09/2018 23:50 - 02/10/2018 00:00"}}
{"2018-00000442": {"category": "Alcohol", "address": "1720 UNIVERSITY AVE Boulder CO", "date": "02/10/2018 00:10 - 02/10/2018 00:29"}}
{"2018-00000443": {"category": "Alcohol", "address": "1720 UNIVERSITY AVE Boulder CO", "date": "02/10/2018 00:22 - 02/10/2018 00:41"}}
{"2018-00000444": {"category": "Drug", "address": "1001 COCKERELL DR Boulder CO", "date": "02/10/2018 00:29 - 02/10/2018 00:29"}}
{"2018-00000445": {"category": "Drug", "address": "2200 WILLARD LOOP DR Boulder CO", "date": "02/10/2018 01:14 - 02/10/2018 01:31"}}
{"2018-00000446": {"category": "Criminal", "address": "4001 DISCOVERY DR Boulder CO", "date": "02/10/2018 01:20 - 02/10/2018 01:20"}}
{"2018-00000448": {"category": "Alcohol", "address": "510 30TH ST Boulder CO", "date": "02/10/2018 02:02 - 02/10/2018 02:52"}}
{"2018-00000449": {"category": "Disturbance", "address": "600 30TH ST Boulder CO", "date": "02/10/2018 02:27 - 02/10/2018 02:27"}}
{"2018-00000455": {"category": "Drug", "address": "2525 KITTREDGE LOOP DR Boulder CO", "date": "02/10/2018 20:47 - 02/10/2018 21:16"}}
{"2018-00000455": {"category": "Drug", "address": "2525 KITTREDGE LOOP DR Boulder CO", "date": "02/10/2018 20:47 - 02/10/2018 21:16"}}
{"2018-00000458": {"category": "Alcohol", "address": "2115 BAKER DR Boulder CO", "date": "02/10/2018 22:05 - 02/10/2018 22:17"}}
{"2018-00000459": {"category": "Drug", "address": "2115 BAKER DR Boulder CO", "date": "02/10/2018 22:31 - 02/10/2018 23:00"}}
{"2018-00000460": {"category": "Drug", "address": "600 30TH ST Boulder CO", "date": "02/10/2018 23:42 - 02/10/2018 23:59"}}
{"2018-00000694": {"category": "DUI/DWAI", "address": "BROADWAY /  UNIVERSITY Boulder CO", "date": "02/27/2018 23:36 - 02/28/2018 02:09"}}
{"2018-00000694": {"category": "DUI/DWAI", "address": "BROADWAY /  UNIVERSITY Boulder CO", "date": "02/27/2018 23:36 - 02/28/2018 02:09"}}
{"2018-00000694": {"category": "DUI/DWAI", "address": "BROADWAY /  UNIVERSITY Boulder CO", "date": "02/27/2018 23:36 - 02/28/2018 02:09"}}
{"2018-00000694": {"category": "DUI/DWAI", "address": "BROADWAY /  UNIVERSITY Boulder CO", "date": "02/27/2018 23:36 - 02/28/2018 02:09"}}
{"2018-00000694": {"category": "DUI/DWAI", "address": "BROADWAY /  UNIVERSITY Boulder CO", "date": "02/27/2018 23:36 - 02/28/2018 02:09"}}
{"2018-00000694": {"category": "DUI/DWAI", "address": "BROADWAY /  UNIVERSITY Boulder CO", "date": "02/27/2018 23:36 - 02/28/2018 02:09"}}
{"2018-00000699": {"category": "Traffic", "address": "2450 KITTREDGE LOOP DR Boulder CO", "date": "02/28/2018 12:55 - 02/28/2018 12:55"}}
{"2018-00000699": {"category": "Traffic", "address": "2450 KITTREDGE LOOP DR Boulder CO", "date": "02/28/2018 12:55 - 02/28/2018 12:55"}}
{"2018-00000700": {"category": "Other", "address": "1610 PLEASANT ST Boulder CO", "date": "02/28/2018 01:00 - 02/28/2018 01:00"}}
{"2018-00000702": {"category": "Drug", "address": "960 GREEN MOUNTAIN DR Boulder CO", "date": "02/28/2018 19:56 - 02/28/2018 20:33"}}
{"2018-00000702": {"category": "Drug", "address": "960 GREEN MOUNTAIN DR Boulder CO", "date": "02/28/2018 19:56 - 02/28/2018 20:33"}}
{"2018-00000703": {"category": "Criminal", "address": "600 30TH ST Boulder CO", "date": "02/28/2018 20:30 - 02/28/2018 20:30"}}
{"2018-00000705": {"category": "Drug", "address": "2115 BAKER DR Boulder CO", "date": "02/28/2018 21:11 - 02/28/2018 21:30"}}
{"2018-00000705": {"category": "Drug", "address": "2115 BAKER DR Boulder CO", "date": "02/28/2018 21:11 - 02/28/2018 21:30"}}
{"2018-00000706": {"category": "Drug", "address": "2200 WILLARD LOOP DR Boulder CO", "date": "02/28/2018 22:05 - 02/28/2018 22:40"}}
{"2018-00000706": {"category": "Drug", "address": "2200 WILLARD LOOP DR Boulder CO", "date": "02/28/2018 22:05 - 02/28/2018 22:40"}}
{"2018-00008148": {"category": "Theft", "address": "1610 PLEASANT ST Boulder CO", "date": "02/28/2018 10:00 - 02/28/2018 15:30"}}
{"2018-00008150": {"category": "Theft", "address": "2115 BAKER DR Boulder CO", "date": "02/28/2018 13:55 - 02/28/2018 15:45"}}
{"2018-00008150": {"category": "Theft", "address": "2115 BAKER DR Boulder CO", "date": "02/28/2018 13:55 - 02/28/2018 15:45"}}
{"2018-00000217": {"category": "Criminal", "address": "4001 DISCOVERY DR Boulder CO", "date": "01/24/2018 00:30 - 01/24/2018 07:00"}}
{"2018-00000217": {"category": "Criminal", "address": "4001 DISCOVERY DR Boulder CO", "date": "01/24/2018 00:30 - 01/24/2018 07:00"}}
{"2018-00000222": {"category": "Theft", "address": "3415 COLORADO AVE Boulder CO", "date": "01/24/2018 16:30 - 01/24/2018 16:30"}}
{"2018-00000226": {"category": "Drug", "address": "1720 UNIVERSITY AVE Boulder CO", "date": "01/25/2018 00:09 - 01/25/2018 00:45"}}
{"2018-00000226": {"category": "Drug", "address": "1720 UNIVERSITY AVE Boulder CO", "date": "01/25/2018 00:09 - 01/25/2018 00:45"}}
{"2018-00000227": {"category": "Other", "address": "2950 BASELINE RD Boulder CO", "date": "01/25/2018 02:00 - 01/25/2018 02:00"}}
{"2018-00000231": {"category": "Drug", "address": "600 30TH ST Boulder CO", "date": "01/25/2018 19:34 - 01/25/2018 19:54"}}
{"2018-00000232": {"category": "Criminal", "address": "1720 UNIVERSITY AVE Boulder CO", "date": "01/25/2018 03:00 - 01/25/2018 03:00"}}
{"2018-00000234": {"category": "Drug", "address": "2005 BAKER DR Boulder CO", "date": "01/25/2018 22:00 - 01/25/2018 22:30"}}
{"2018-00000234": {"category": "Drug", "address": "2005 BAKER DR Boulder CO", "date": "01/25/2018 22:00 - 01/25/2018 22:30"}}
{"2018-00000235": {"category": "Alcohol", "address": "1665 CENTRAL CAMPUS Boulder CO", "date": "01/25/2018 22:50 - 01/25/2018 23:28"}}
{"2018-00000403": {"category": "Theft", "address": "2525 KITTREDGE LOOP DR Boulder CO", "date": "02/08/2018 03:44 - 02/08/2018 03:47"}}
{"2018-00000403": {"category": "Theft", "address": "2525 KITTREDGE LOOP DR Boulder CO", "date": "02/08/2018 03:44 - 02/08/2018 03:47"}}
{"2018-00000468": {"category": "Warrant", "address": "1300 30TH ST Boulder CO", "date": "02/12/2018 01:00 - 02/12/2018 01:00"}}
{"2018-00000470": {"category": "Criminal", "address": "1111 ENGINEERING DR Boulder CO", "date": "02/12/2018 04:40 - 02/12/2018 05:00"}}
{"2018-00000473": {"category": "Traffic", "address": "2360 COLORADO AVE Boulder CO", "date": "02/12/2018 13:00 - 02/12/2018 13:00"}}
{"2018-00000474": {"category": "Sex", "address": "4001 DISCOVERY DR Boulder CO", "date": "02/12/2018 12:42 - 02/12/2018 12:42"}}
{"2018-00000475": {"category": "Traffic", "address": "WARDENBURG DR /  18TH ST Boulder CO", "date": "02/12/2018 15:25 - 02/12/2018 15:25"}}
{"2018-00000477": {"category": "Drug", "address": "1855 ATHENS ST Boulder CO", "date": "02/12/2018 19:01 - 02/12/2018 19:45"}}
{"2018-00000477": {"category": "Drug", "address": "1855 ATHENS ST Boulder CO", "date": "02/12/2018 19:01 - 02/12/2018 19:45"}}
{"2018-00000480": {"category": "Drug", "address": "2250 WILLARD LOOP DR Boulder CO", "date": "02/12/2018 22:15 - 02/12/2018 22:15"}}
{"2018-00000481": {"category": "Drug", "address": "2605 KITTREDGE LOOP DR Boulder CO", "date": "02/12/2018 22:58 - 02/12/2018 23:20"}}
{"2018-00000446": {"category": "Criminal", "address": "4001 DISCOVERY DR Boulder CO", "date": "02/10/2018 01:20 - 02/10/2018 01:20"}}
{"2018-00000616": {"category": "Traffic", "address": "18TH ST /  EUCLID AVE Boulder CO", "date": "02/21/2018 08:50 - 02/21/2018 08:50"}}
{"2018-00000622": {"category": "Traffic", "address": "1540 PLEASANT ST Boulder CO", "date": "02/21/2018 13:30 - 02/21/2018 13:30"}}
{"2018-00000624": {"category": "Drug", "address": "600 30TH ST Boulder CO", "date": "02/21/2018 20:33 - 02/21/2018 21:02"}}
{"2018-00008129": {"category": "Theft", "address": "1350 20TH ST Boulder CO", "date": "02/19/2018 12:30 - 02/21/2018 12:30"}}
{"2018-00000723": {"category": "Traffic", "address": "2180 REGENT DR Boulder CO", "date": "03/02/2018 14:39 - 03/02/2018 14:39"}}
{"2018-00000747": {"category": "Other", "address": "3625 DISCOVERY DR Boulder CO", "date": "03/03/2018 23:09 - 03/04/2018 01:24"}}
{"2018-00000747": {"category": "Other", "address": "3625 DISCOVERY DR Boulder CO", "date": "03/03/2018 23:09 - 03/04/2018 01:24"}}
{"2018-00000747": {"category": "Other", "address": "3625 DISCOVERY DR Boulder CO", "date": "03/03/2018 23:09 - 03/04/2018 01:24"}}
{"2018-00000748": {"category": "Traffic", "address": "900 REGENT DR Boulder CO", "date": "03/03/2018 23:12 - 03/03/2018 23:12"}}
{"2018-00000748": {"category": "Traffic", "address": "900 REGENT DR Boulder CO", "date": "03/03/2018 23:12 - 03/03/2018 23:12"}}
{"2018-00000748": {"category": "Traffic", "address": "900 REGENT DR Boulder CO", "date": "03/03/2018 23:12 - 03/03/2018 23:12"}}
{"2018-00000748": {"category": "Traffic", "address": "900 REGENT DR Boulder CO", "date": "03/03/2018 23:12 - 03/03/2018 23:12"}}
{"2018-00000749": {"category": "Warrant", "address": "1720 UNIVERSITY AVE Boulder CO", "date": "03/03/2018 23:58 - 03/03/2018 23:58"}}
{"2018-00000751": {"category": "Alcohol", "address": "1720 UNIVERSITY AVE Boulder CO", "date": "03/04/2018 00:20 - 03/04/2018 00:20"}}
{"2018-00000751": {"category": "Alcohol", "address": "1720 UNIVERSITY AVE Boulder CO", "date": "03/04/2018 00:20 - 03/04/2018 00:20"}}
{"2018-00000752": {"category": "Alcohol", "address": "500 30TH ST Boulder CO", "date": "03/04/2018 01:45 - 03/04/2018 02:19"}}
{"2018-00000753": {"category": "Drug", "address": "600 30TH ST Boulder CO", "date": "03/04/2018 01:25 - 03/04/2018 01:45"}}
{"2018-00000754": {"category": "Drug", "address": "1720 UNIVERSITY AVE Boulder CO", "date": "03/04/2018 01:57 - 03/04/2018 02:18"}}
{"2018-00000755": {"category": "Alcohol", "address": "1445 CENTRAL CAMPUS Boulder CO", "date": "03/04/2018 02:40 - 03/04/2018 02:40"}}
{"2018-00000757": {"category": "Motor", "address": "3359 APACHE RD Boulder CO", "date": "03/04/2018 16:14 - 03/04/2018 16:14"}}
{"2018-00000757": {"category": "Motor", "address": "3359 APACHE RD Boulder CO", "date": "03/04/2018 16:14 - 03/04/2018 16:14"}}
{"2018-00000758": {"category": "Drug", "address": "600 30TH ST Boulder CO", "date": "03/04/2018 20:10 - 03/04/2018 20:45"}}
{"2018-00000758": {"category": "Drug", "address": "600 30TH ST Boulder CO", "date": "03/04/2018 20:10 - 03/04/2018 20:45"}}
{"2018-00000760": {"category": "Alcohol", "address": "600 30TH ST Boulder CO", "date": "03/04/2018 21:10 - 03/04/2018 21:35"}}
{"2018-00000760": {"category": "Alcohol", "address": "600 30TH ST Boulder CO", "date": "03/04/2018 21:10 - 03/04/2018 21:35"}}
{"2018-00000761": {"category": "Drug", "address": "960 GREEN MOUNTAIN DR Boulder CO", "date": "03/04/2018 21:21 - 03/04/2018 21:42"}}
{"2018-00000762": {"category": "Drug", "address": "600 30TH ST Boulder CO", "date": "03/04/2018 21:48 - 03/04/2018 22:30"}}
{"2018-00000762": {"category": "Drug", "address": "600 30TH ST Boulder CO", "date": "03/04/2018 21:48 - 03/04/2018 22:30"}}
{"2018-00000763": {"category": "Other", "address": "3355 APACHE RD Boulder CO", "date": "03/04/2018 22:19 - 03/04/2018 22:19"}}
{"2018-00000763": {"category": "Other", "address": "3355 APACHE RD Boulder CO", "date": "03/04/2018 22:19 - 03/04/2018 22:19"}}
{"2018-00008157": {"category": "Theft", "address": "3300 BASELINE RD Boulder CO", "date": "01/25/2018 12:00 - 01/30/2018 12:00"}}
{"2018-00008158": {"category": "Theft", "address": "2005 BAKER DR Boulder CO", "date": "03/01/2018 16:00 - 03/02/2018 11:00"}}
{"2018-00008158": {"category": "Theft", "address": "2005 BAKER DR Boulder CO", "date": "03/01/2018 16:00 - 03/02/2018 11:00"}}
{"2018-00000488": {"category": "Other", "address": "2450 KITTREDGE LOOP DR Boulder CO", "date": "02/13/2018 14:45 - 02/13/2018 14:45"}}
{"2018-00000541": {"category": "Theft", "address": "2450 KITTREDGE LOOP DR Boulder CO", "date": "02/16/2018 16:00 - 02/16/2018 16:00"}}
{"2018-00000547": {"category": "Criminal", "address": "2085 COLORADO AVE Boulder CO", "date": "02/16/2018 23:12 - 02/16/2018 23:12"}}
{"2018-00000577": {"category": "Other", "address": "1521 CENTRAL CAMPUS Boulder CO", "date": "02/18/2018 01:27 - 02/18/2018 01:27"}}
{"2018-00000577": {"category": "Other", "address": "1521 CENTRAL CAMPUS Boulder CO", "date": "02/18/2018 01:27 - 02/18/2018 01:27"}}
{"2018-00000589": {"category": "Criminal", "address": "2320 LIBBY DR Boulder CO", "date": "02/19/2018 00:02 - 02/19/2018 00:02"}}
{"2018-00000590": {"category": "Drug", "address": "2320 LIBBY DR Boulder CO", "date": "02/19/2018 00:21 - 02/19/2018 00:40"}}
{"2018-00000590": {"category": "Drug", "address": "2320 LIBBY DR Boulder CO", "date": "02/19/2018 00:21 - 02/19/2018 00:40"}}
{"2018-00000591": {"category": "Other", "address": "5278 TABLE MESA DR Boulder CO", "date": "02/17/2018 22:30 - 02/19/2018 03:10"}}
{"2018-00000592": {"category": "Fraud/Forgery", "address": "1050 REGENT DR Boulder CO", "date": "02/14/2018 08:00 - 02/15/2018 08:30"}}
{"2018-00000593": {"category": "Fraud/Forgery", "address": "1669 EUCLID AVE Boulder CO", "date": "02/16/2018 08:00 - 02/16/2018 08:00"}}
{"2018-00000600": {"category": "Assist", "address": "1855 GOSS ST Boulder CO", "date": "02/19/2018 18:36 - 02/19/2018 18:56"}}
{"2018-00000602": {"category": "Drug", "address": "500 30TH ST Boulder CO", "date": "02/19/2018 20:46 - 02/19/2018 21:11"}}
{"2018-00000602": {"category": "Drug", "address": "500 30TH ST Boulder CO", "date": "02/19/2018 20:46 - 02/19/2018 21:11"}}
{"2018-00000603": {"category": "Warrant", "address": "1720 UNIVERSITY AVE Boulder CO", "date": "02/19/2018 22:30 - 02/19/2018 22:30"}}
{"2018-00000603": {"category": "Warrant", "address": "1720 UNIVERSITY AVE Boulder CO", "date": "02/19/2018 22:30 - 02/19/2018 22:30"}}
{"2018-00000604": {"category": "Traffic", "address": "1720 UNIVERSITY AVE Boulder CO", "date": "02/19/2018 21:00 - 02/19/2018 21:00"}}
{"2018-00000604": {"category": "Traffic", "address": "1720 UNIVERSITY AVE Boulder CO", "date": "02/19/2018 21:00 - 02/19/2018 21:00"}}
{"2018-00008123": {"category": "Theft", "address": "1855 PLEASANT ST Boulder CO", "date": "02/15/2018 21:19 - 02/15/2018 23:02"}}
{"2018-00000474": {"category": "Sex", "address": "4001 DISCOVERY DR Boulder CO", "date": "02/12/2018 12:42 - 02/12/2018 12:42"}}
{"2018-00000605": {"category": "Alcohol", "address": "2200 BAKER DR Boulder CO", "date": "02/19/2018 23:59 - 02/20/2018 00:14"}}
{"2018-00000607": {"category": "Drug", "address": "2005 BAKER DR Boulder CO", "date": "02/20/2018 00:46 - 02/20/2018 01:01"}}
{"2018-00000608": {"category": "Theft", "address": "2115 BAKER DR Boulder CO", "date": "02/20/2018 01:10 - 02/20/2018 01:10"}}
{"2018-00000609": {"category": "Drug", "address": "2250 WILLARD LOOP DR Boulder CO", "date": "02/20/2018 01:34 - 02/20/2018 01:57"}}
{"2018-00000609": {"category": "Drug", "address": "2250 WILLARD LOOP DR Boulder CO", "date": "02/20/2018 01:34 - 02/20/2018 01:57"}}
{"2018-00000612": {"category": "Assault", "address": "3275 APACHE RD Boulder CO", "date": "02/20/2018 18:56 - 02/20/2018 18:56"}}
{"2018-00000612": {"category": "Assault", "address": "3275 APACHE RD Boulder CO", "date": "02/20/2018 18:56 - 02/20/2018 18:56"}}
{"2018-00000612": {"category": "Assault", "address": "3275 APACHE RD Boulder CO", "date": "02/20/2018 18:56 - 02/20/2018 18:56"}}
{"2018-00000613": {"category": "Drug", "address": "600 30TH ST Boulder CO", "date": "02/20/2018 21:34 - 02/20/2018 22:05"}}
{"2018-00000613": {"category": "Drug", "address": "600 30TH ST Boulder CO", "date": "02/20/2018 21:34 - 02/20/2018 22:05"}}
{"2018-00000614": {"category": "Drug", "address": "500 30TH ST Boulder CO", "date": "02/20/2018 23:01 - 02/20/2018 23:01"}}
{"2018-00000614": {"category": "Drug", "address": "500 30TH ST Boulder CO", "date": "02/20/2018 23:01 - 02/20/2018 23:01"}}
{"2018-00000358": {"category": "Traffic", "address": "30TH ST /  EUCLID AVE Boulder CO", "date": "02/04/2018 00:49 - 02/04/2018 01:40"}}
{"2018-00000358": {"category": "Traffic", "address": "30TH ST /  EUCLID AVE Boulder CO", "date": "02/04/2018 00:49 - 02/04/2018 01:40"}}
{"2018-00000358": {"category": "Traffic", "address": "30TH ST /  EUCLID AVE Boulder CO", "date": "02/04/2018 00:49 - 02/04/2018 01:40"}}
{"2018-00000358": {"category": "Traffic", "address": "30TH ST /  EUCLID AVE Boulder CO", "date": "02/04/2018 00:49 - 02/04/2018 01:40"}}
{"2018-00000359": {"category": "Drug", "address": "2370 LIBBY DR Boulder CO", "date": "02/04/2018 00:58 - 02/04/2018 01:57"}}
{"2018-00000359": {"category": "Drug", "address": "2370 LIBBY DR Boulder CO", "date": "02/04/2018 00:58 - 02/04/2018 01:57"}}
{"2018-00000359": {"category": "Drug", "address": "2370 LIBBY DR Boulder CO", "date": "02/04/2018 00:58 - 02/04/2018 01:57"}}
{"2018-00000363": {"category": "Alcohol", "address": "2005 BAKER DR Boulder CO", "date": "02/04/2018 20:45 - 02/04/2018 21:08"}}
{"2018-00000364": {"category": "Alcohol", "address": "2350 LIBBY DR Boulder CO", "date": "02/04/2018 21:14 - 02/04/2018 21:37"}}
{"2018-00000365": {"category": "Drug", "address": "960 GREEN MOUNTAIN DR Boulder CO", "date": "02/04/2018 21:12 - 02/04/2018 21:30"}}
{"2018-00000366": {"category": "Drug", "address": "960 GREEN MOUNTAIN DR Boulder CO", "date": "02/04/2018 21:37 - 02/04/2018 21:55"}}
{"2018-00000368": {"category": "DUI/DWAI", "address": "BASELINE RD /  BROADWAY Boulder CO", "date": "02/04/2018 23:51 - 02/05/2018 02:50"}}
{"2018-00000368": {"category": "DUI/DWAI", "address": "BASELINE RD /  BROADWAY Boulder CO", "date": "02/04/2018 23:51 - 02/05/2018 02:50"}}
{"2018-00000368": {"category": "DUI/DWAI", "address": "BASELINE RD /  BROADWAY Boulder CO", "date": "02/04/2018 23:51 - 02/05/2018 02:50"}}
{"2018-00000368": {"category": "DUI/DWAI", "address": "BASELINE RD /  BROADWAY Boulder CO", "date": "02/04/2018 23:51 - 02/05/2018 02:50"}}
{"2018-00000368": {"category": "DUI/DWAI", "address": "BASELINE RD /  BROADWAY Boulder CO", "date": "02/04/2018 23:51 - 02/05/2018 02:50"}}
{"2018-00000368": {"category": "DUI/DWAI", "address": "BASELINE RD /  BROADWAY Boulder CO", "date": "02/04/2018 23:51 - 02/05/2018 02:50"}}
{"2018-00000194": {"category": "Drug", "address": "2200 BAKER DR Boulder CO", "date": "01/22/2018 23:29 - 01/23/2018 00:00"}}
{"2018-00000194": {"category": "Drug", "address": "2200 BAKER DR Boulder CO", "date": "01/22/2018 23:29 - 01/23/2018 00:00"}}
{"2018-00000194": {"category": "Drug", "address": "2200 BAKER DR Boulder CO", "date": "01/22/2018 23:29 - 01/23/2018 00:00"}}
{"2018-00000197": {"category": "Drug", "address": "3300 BASELINE RD Boulder CO", "date": "01/23/2018 01:01 - 01/23/2018 01:33"}}
{"2018-00000197": {"category": "Drug", "address": "3300 BASELINE RD Boulder CO", "date": "01/23/2018 01:01 - 01/23/2018 01:33"}}
{"2018-00000198": {"category": "Traffic", "address": "18TH ST /  EUCLID AVE Boulder CO", "date": "01/23/2018 09:00 - 01/23/2018 09:00"}}
{"2018-00000198": {"category": "Traffic", "address": "18TH ST /  EUCLID AVE Boulder CO", "date": "01/23/2018 09:00 - 01/23/2018 09:00"}}
{"2018-00000198": {"category": "Traffic", "address": "18TH ST /  EUCLID AVE Boulder CO", "date": "01/23/2018 09:00 - 01/23/2018 09:00"}}
{"2018-00000200": {"category": "Theft", "address": "1669 EUCLID AVE Boulder CO", "date": "01/23/2018 13:00 - 01/23/2018 13:00"}}
{"2018-00000201": {"category": "Theft", "address": "1669 EUCLID AVE Boulder CO", "date": "01/23/2018 14:25 - 01/23/2018 14:25"}}
{"2018-00000203": {"category": "Harassment", "address": "1050 REGENT DR Boulder CO", "date": "01/23/2018 17:00 - 01/23/2018 17:00"}}
{"2018-00000204": {"category": "Drug", "address": "2250 WILLARD LOOP DR Boulder CO", "date": "01/23/2018 20:10 - 01/23/2018 20:20"}}
{"2018-00000206": {"category": "Drug", "address": "600 30TH ST Boulder CO", "date": "01/23/2018 20:58 - 01/23/2018 21:08"}}
{"2018-00000207": {"category": "Drug", "address": "2605 KITTREDGE LOOP DR Boulder CO", "date": "01/23/2018 21:50 - 01/23/2018 22:30"}}
{"2018-00000207": {"category": "Drug", "address": "2605 KITTREDGE LOOP DR Boulder CO", "date": "01/23/2018 21:50 - 01/23/2018 22:30"}}
{"2018-00000208": {"category": "Criminal", "address": "4001 DISCOVERY DR Boulder CO", "date": "01/23/2018 19:55 - 01/23/2018 22:26"}}
{"2018-00000209": {"category": "Drug", "address": "960 GREEN MOUNTAIN DR Boulder CO", "date": "01/23/2018 22:52 - 01/23/2018 22:52"}}
{"2018-00000209": {"category": "Drug", "address": "960 GREEN MOUNTAIN DR Boulder CO", "date": "01/23/2018 22:52 - 01/23/2018 22:52"}}
{"2018-00000209": {"category": "Drug", "address": "960 GREEN MOUNTAIN DR Boulder CO", "date": "01/23/2018 22:52 - 01/23/2018 22:52"}}
{"2018-00000210": {"category": "Criminal", "address": "960 GREEN MOUNTAIN DR Boulder CO", "date": "01/23/2018 20:00 - 01/23/2018 22:30"}}
{"2018-00008017": {"category": "Theft", "address": "2200 BAKER DR Boulder CO", "date": "12/21/2017 10:45 - 01/13/2018 10:45"}}
{"2018-00008047": {"category": "Theft", "address": "2525 KITTREDGE LOOP DR Boulder CO", "date": "01/23/2018 16:30 - 01/23/2018 16:40"}}
{"2018-00000251": {"category": "Drug", "address": "1720 UNIVERSITY AVE Boulder CO", "date": "01/26/2018 23:39 - 01/27/2018 00:15"}}
{"2018-00000251": {"category": "Drug", "address": "1720 UNIVERSITY AVE Boulder CO", "date": "01/26/2018 23:39 - 01/27/2018 00:15"}}
{"2018-00000252": {"category": "Drug", "address": "2200 BAKER DR Boulder CO", "date": "01/27/2018 00:48 - 01/27/2018 01:00"}}
{"2018-00000252": {"category": "Drug", "address": "2200 BAKER DR Boulder CO", "date": "01/27/2018 00:48 - 01/27/2018 01:00"}}
{"2018-00000253": {"category": "DUI/DWAI", "address": "38TH ST /  COLORADO AVE Boulder CO", "date": "01/27/2018 01:34 - 01/27/2018 04:00"}}
{"2018-00000253": {"category": "DUI/DWAI", "address": "38TH ST /  COLORADO AVE Boulder CO", "date": "01/27/2018 01:34 - 01/27/2018 04:00"}}
{"2018-00000254": {"category": "Other", "address": "1595 PLEASANT ST Boulder CO", "date": "01/27/2018 03:01 - 01/27/2018 03:01"}}
{"2018-00000255": {"category": "Other", "address": "BROADWAY /  Boulder CO", "date": "01/27/2018 03:16 - 01/27/2018 04:00"}}
{"2018-00000255": {"category": "Other", "address": "BROADWAY /  Boulder CO", "date": "01/27/2018 03:16 - 01/27/2018 04:00"}}
{"2018-00000255": {"category": "Other", "address": "BROADWAY /  Boulder CO", "date": "01/27/2018 03:16 - 01/27/2018 04:00"}}
{"2018-00000255": {"category": "Other", "address": "BROADWAY /  Boulder CO", "date": "01/27/2018 03:16 - 01/27/2018 04:00"}}
{"2018-00000257": {"category": "Alcohol", "address": "600 30TH ST Boulder CO", "date": "01/27/2018 03:45 - 01/27/2018 03:45"}}
{"2018-00000258": {"category": "Criminal", "address": "2180 REGENT DR Boulder CO", "date": "01/26/2018 11:14 - 01/27/2018 10:16"}}
{"2018-00000258": {"category": "Criminal", "address": "2180 REGENT DR Boulder CO", "date": "01/26/2018 11:14 - 01/27/2018 10:16"}}
{"2018-00000262": {"category": "Drug", "address": "2200 WILLARD LOOP DR Boulder CO", "date": "01/27/2018 21:00 - 01/27/2018 21:38"}}
{"2018-00000262": {"category": "Drug", "address": "2200 WILLARD LOOP DR Boulder CO", "date": "01/27/2018 21:00 - 01/27/2018 21:38"}}
{"2018-00000263": {"category": "Theft", "address": "3645 MARINE ST Boulder CO", "date": "01/27/2018 21:55 - 01/27/2018 21:55"}}
{"2018-00000264": {"category": "Drug", "address": "1720 UNIVERSITY AVE Boulder CO", "date": "01/27/2018 22:01 - 01/27/2018 22:01"}}
{"2018-00000264": {"category": "Drug", "address": "1720 UNIVERSITY AVE Boulder CO", "date": "01/27/2018 22:01 - 01/27/2018 22:01"}}
{"2018-00000265": {"category": "Alcohol", "address": "1720 UNIVERSITY AVE Boulder CO", "date": "01/27/2018 22:44 - 01/27/2018 22:56"}}
{"2018-00000266": {"category": "Warrant", "address": "3625 DISCOVERY DR Boulder CO", "date": "01/27/2018 22:50 - 01/27/2018 22:50"}}
{"2018-00000267": {"category": "Criminal", "address": "3275 APACHE RD Boulder CO", "date": "01/27/2018 23:41 - 01/27/2018 23:41"}}
{"2018-00000268": {"category": "Drug", "address": "3625 DISCOVERY DR Boulder CO", "date": "01/27/2018 22:50 - 01/27/2018 22:50"}}
{"2018-00000268": {"category": "Drug", "address": "3625 DISCOVERY DR Boulder CO", "date": "01/27/2018 22:50 - 01/27/2018 22:50"}}
{"2018-00000268": {"category": "Drug", "address": "3625 DISCOVERY DR Boulder CO", "date": "01/27/2018 22:50 - 01/27/2018 22:50"}}
{"2018-00000268": {"category": "Drug", "address": "3625 DISCOVERY DR Boulder CO", "date": "01/27/2018 22:50 - 01/27/2018 22:50"}}
{"2018-00008054": {"category": "Theft", "address": "1015 COCKERELL DR Boulder CO", "date": "01/26/2018 16:15 - 01/27/2018 08:15"}}
{"2018-00000175": {"category": "Drug", "address": "2115 BAKER DR Boulder CO", "date": "01/21/2018 22:52 - 01/21/2018 22:52"}}
{"2018-00000175": {"category": "Drug", "address": "2115 BAKER DR Boulder CO", "date": "01/21/2018 22:52 - 01/21/2018 22:52"}}
{"2018-00000178": {"category": "Alcohol", "address": "2200 WILLARD LOOP DR Boulder CO", "date": "01/22/2018 00:15 - 01/22/2018 01:52"}}
{"2018-00000179": {"category": "Other", "address": "1550 CENTRAL CAMPUS Boulder CO", "date": "01/22/2018 02:35 - 01/22/2018 02:35"}}
{"2018-00000180": {"category": "Other", "address": "3800 ARAPAHOE AVE Boulder CO", "date": "01/22/2018 08:05 - 01/22/2018 08:05"}}
{"2018-00000185": {"category": "Traffic", "address": "18TH ST /  BROADWAY Boulder CO", "date": "01/22/2018 13:21 - 01/22/2018 13:21"}}
{"2018-00000185": {"category": "Traffic", "address": "18TH ST /  BROADWAY Boulder CO", "date": "01/22/2018 13:21 - 01/22/2018 13:21"}}
{"2018-00000186": {"category": "Sex", "address": "2320 LIBBY DR Boulder CO", "date": "01/21/2018 02:00 - 01/21/2018 02:00"}}
{"2018-00000188": {"category": "Harassment", "address": "960 GREEN MOUNTAIN DR Boulder CO", "date": "01/22/2018 16:00 - 01/22/2018 16:00"}}
{"2018-00000190": {"category": "Drug", "address": "2250 WILLARD LOOP DR Boulder CO", "date": "01/22/2018 23:30 - 01/22/2018 23:30"}}
{"2018-00000190": {"category": "Drug", "address": "2250 WILLARD LOOP DR Boulder CO", "date": "01/22/2018 23:30 - 01/22/2018 23:30"}}
{"2018-00000191": {"category": "Drug", "address": "600 30TH ST Boulder CO", "date": "01/22/2018 22:15 - 01/22/2018 22:45"}}
{"2018-00000193": {"category": "Drug", "address": "2200 BAKER DR Boulder CO", "date": "01/22/2018 22:51 - 01/22/2018 23:19"}}
{"2018-00000193": {"category": "Drug", "address": "2200 BAKER DR Boulder CO", "date": "01/22/2018 22:51 - 01/22/2018 23:19"}}
{"2018-00000194": {"category": "Drug", "address": "2200 BAKER DR Boulder CO", "date": "01/22/2018 23:29 - 01/23/2018 00:00"}}
{"2018-00000194": {"category": "Drug", "address": "2200 BAKER DR Boulder CO", "date": "01/22/2018 23:29 - 01/23/2018 00:00"}}
{"2018-00000194": {"category": "Drug", "address": "2200 BAKER DR Boulder CO", "date": "01/22/2018 23:29 - 01/23/2018 00:00"}}
{"2018-00008042": {"category": "Theft", "address": "2250 WILLARD LOOP DR Boulder CO", "date": "11/17/2017 20:00 - 11/18/2017 08:00"}}
{"2018-00008043": {"category": "Theft", "address": "2480 KITTREDGE LOOP DR Boulder CO", "date": "01/20/2018 14:40 - 01/22/2018 14:40"}}
{"2018-00008044": {"category": "Theft", "address": "1111 ENGINEERING DR Boulder CO", "date": "01/22/2018 10:00 - 01/22/2018 15:15"}}
{"2018-00000318": {"category": "Drug", "address": "2200 WILLARD LOOP DR Boulder CO", "date": "02/01/2018 22:10 - 02/01/2018 22:10"}}
{"2018-00000318": {"category": "Drug", "address": "2200 WILLARD LOOP DR Boulder CO", "date": "02/01/2018 22:10 - 02/01/2018 22:10"}}
{"2018-00000320": {"category": "Other", "address": "1900 GRANDVIEW AVE Boulder CO", "date": "02/02/2018 05:02 - 02/02/2018 05:02"}}
{"2018-00000327": {"category": "Traffic", "address": "BROADWAY /  ARAPAHOE Boulder CO", "date": "02/02/2018 08:45 - 02/02/2018 08:45"}}
{"2018-00000333": {"category": "Fraud/Forgery", "address": "1475 FOLSOM ST Boulder CO", "date": "02/02/2018 15:00 - 02/02/2018 18:00"}}
{"2018-00000335": {"category": "Drug", "address": "2115 BAKER DR Boulder CO", "date": "02/02/2018 20:00 - 02/02/2018 20:37"}}
{"2018-00000336": {"category": "Theft", "address": "1720 UNIVERSITY AVE Boulder CO", "date": "02/02/2018 20:28 - 02/02/2018 20:28"}}
{"2018-00000336": {"category": "Theft", "address": "1720 UNIVERSITY AVE Boulder CO", "date": "02/02/2018 20:28 - 02/02/2018 20:28"}}
{"2018-00000338": {"category": "Drug", "address": "2250 WILLARD LOOP DR Boulder CO", "date": "02/02/2018 21:45 - 02/02/2018 21:53"}}
{"2018-00000338": {"category": "Drug", "address": "2250 WILLARD LOOP DR Boulder CO", "date": "02/02/2018 21:45 - 02/02/2018 21:53"}}
{"2018-00000340": {"category": "Alcohol", "address": "505 27TH WAY Boulder CO", "date": "02/02/2018 23:18 - 02/02/2018 23:18"}}
{"2018-00008080": {"category": "Theft", "address": "2400 KITTREDGE LOOP DR Boulder CO", "date": "01/29/2018 17:20 - 01/31/2018 05:20"}}
{"2018-00008081": {"category": "Property", "address": "1720 UNIVERSITY AVE Boulder CO", "date": "02/01/2018 17:30 - 02/02/2018 00:55"}}
{"2018-00008083": {"category": "Theft", "address": "3275 APACHE RD Boulder CO", "date": "01/31/2018 21:00 - 02/02/2018 09:00"}}
{"2018-00008083": {"category": "Theft", "address": "3275 APACHE RD Boulder CO", "date": "01/31/2018 21:00 - 02/02/2018 09:00"}}
{"2018-00008085": {"category": "Theft", "address": "1475 FOLSOM ST Boulder CO", "date": "02/01/2018 17:00 - 02/02/2018 11:00"}}
{"2017-00008522": {"category": "Theft", "address": "2300 ARAPAHOE AVE Boulder CO", "date": "10/10/2017 00:10 - 10/10/2017 10:00"}}
{"2018-00000276": {"category": "Accident", "address": "1050 REGENT DR Boulder CO", "date": "01/29/2018 10:22 - 01/29/2018 10:22"}}
{"2018-00000278": {"category": "Theft", "address": "1669 EUCLID AVE Boulder CO", "date": "01/29/2018 10:55 - 01/29/2018 10:55"}}
{"2018-00000279": {"category": "Fraud/Forgery", "address": "2249 WILLARD LOOP DR Boulder CO", "date": "01/29/2018 14:09 - 01/29/2018 15:20"}}
{"2018-00000281": {"category": "Drug", "address": "2200 BAKER DR Boulder CO", "date": "01/29/2018 20:20 - 01/29/2018 20:49"}}
{"2018-00000282": {"category": "Drug", "address": "1720 UNIVERSITY AVE Boulder CO", "date": "01/29/2018 20:50 - 01/29/2018 21:06"}}
{"2018-00008060": {"category": "Theft", "address": "500 30TH ST Boulder CO", "date": "01/27/2018 16:30 - 01/29/2018 11:30"}}
{"2018-00008062": {"category": "Theft", "address": "1720 UNIVERSITY AVE Boulder CO", "date": "01/28/2018 11:00 - 01/28/2018 12:00"}}
{"2018-00008062": {"category": "Theft", "address": "1720 UNIVERSITY AVE Boulder CO", "date": "01/28/2018 11:00 - 01/28/2018 12:00"}}
{"2018-00008065": {"category": "Theft", "address": "2480 KITTREDGE LOOP DR Boulder CO", "date": "01/29/2018 17:45 - 01/29/2018 17:45"}}
{"2018-00008067": {"category": "Theft", "address": "2200 BAKER DR Boulder CO", "date": "01/29/2018 18:30 - 01/29/2018 18:30"}}
{"2018-00000721": {"category": "Theft", "address": "3215 MARINE ST Boulder CO", "date": "02/21/2018 11:08 - 03/02/2018 11:08"}}
{"2018-00000791": {"category": "Criminal", "address": "1775 CENTRAL CAMPUS Boulder CO", "date": "03/07/2018 08:45 - 03/07/2018 08:45"}}
{"2018-00000793": {"category": "Sex", "address": "1515 CENTRAL CAMPUS Boulder CO", "date": "02/24/2018 00:00 - 02/25/2018 23:59"}}
{"2018-00000794": {"category": "Theft", "address": "1855 PLEASANT ST Boulder CO", "date": "03/07/2018 14:00 - 03/07/2018 15:45"}}
{"2018-00000795": {"category": "Suspicious", "address": "3300 BASELINE RD Boulder CO", "date": "03/05/2018 16:00 - 03/07/2018 18:08"}}
{"2018-00000795": {"category": "Suspicious", "address": "3300 BASELINE RD Boulder CO", "date": "03/05/2018 16:00 - 03/07/2018 18:08"}}
{"2018-00000796": {"category": "Drug", "address": "2605 KITTREDGE LOOP DR Boulder CO", "date": "03/07/2018 19:50 - 03/07/2018 20:19"}}
{"2018-00000796": {"category": "Drug", "address": "2605 KITTREDGE LOOP DR Boulder CO", "date": "03/07/2018 19:50 - 03/07/2018 20:19"}}
{"2018-00000798": {"category": "Drug", "address": "2115 BAKER DR Boulder CO", "date": "03/07/2018 20:33 - 03/07/2018 21:06"}}
{"2018-00000798": {"category": "Drug", "address": "2115 BAKER DR Boulder CO", "date": "03/07/2018 20:33 - 03/07/2018 21:06"}}
{"2018-00000799": {"category": "Drug", "address": "2590 KITTREDGE LOOP DR Boulder CO", "date": "03/07/2018 21:03 - 03/07/2018 21:27"}}
{"2018-00000799": {"category": "Drug", "address": "2590 KITTREDGE LOOP DR Boulder CO", "date": "03/07/2018 21:03 - 03/07/2018 21:27"}}
{"2018-00008163": {"category": "Criminal", "address": "1546 BROADWAY Boulder CO", "date": "03/07/2018 07:20 - 03/07/2018 07:20"}}
{"2018-00000722": {"category": "Theft", "address": "1157 18TH ST Boulder CO", "date": "03/02/2018 13:36 - 03/02/2018 13:36"}}
{"2018-00000729": {"category": "Assault", "address": "1335 BROADWAY Boulder CO", "date": "03/03/2018 00:03 - 03/03/2018 03:13"}}
{"2018-00000729": {"category": "Assault", "address": "1335 BROADWAY Boulder CO", "date": "03/03/2018 00:03 - 03/03/2018 03:13"}}
{"2018-00000729": {"category": "Assault", "address": "1335 BROADWAY Boulder CO", "date": "03/03/2018 00:03 - 03/03/2018 03:13"}}
{"2018-00000731": {"category": "Alcohol", "address": "2200 BAKER DR Boulder CO", "date": "03/03/2018 01:40 - 03/03/2018 01:40"}}
{"2018-00000732": {"category": "Disturbance", "address": "500 30TH ST Boulder CO", "date": "03/03/2018 01:54 - 03/03/2018 01:54"}}
{"2018-00000734": {"category": "Alcohol", "address": "1202 UNIVERSITY AVE Boulder CO", "date": "03/03/2018 23:45 - 03/03/2018 23:45"}}
{"2018-00000735": {"category": "Alcohol", "address": "1900 WARDENBURG DR Boulder CO", "date": "03/03/2018 03:03 - 03/03/2018 03:03"}}
{"2018-00000738": {"category": "Traffic", "address": "900 REGENT DR Boulder CO", "date": "03/03/2018 11:45 - 03/03/2018 11:45"}}
{"2018-00000738": {"category": "Traffic", "address": "900 REGENT DR Boulder CO", "date": "03/03/2018 11:45 - 03/03/2018 11:45"}}
{"2018-00000738": {"category": "Traffic", "address": "900 REGENT DR Boulder CO", "date": "03/03/2018 11:45 - 03/03/2018 11:45"}}
{"2018-00000741": {"category": "Alcohol", "address": "2250 WILLARD LOOP DR Boulder CO", "date": "03/03/2018 20:01 - 03/03/2018 20:25"}}
{"2018-00000742": {"category": "Other", "address": "3300 BASELINE RD Boulder CO", "date": "03/03/2018 20:55 - 03/03/2018 20:55"}}
{"2018-00000743": {"category": "Suspicious", "address": "1720 UNIVERSITY AVE Boulder CO", "date": "03/03/2018 18:10 - 03/03/2018 20:40"}}
{"2018-00000745": {"category": "Alcohol", "address": "COLORADO AVE /  LIBBY DR Boulder CO", "date": "03/03/2018 02:40 - 03/03/2018 02:40"}}
{"2018-00000747": {"category": "Other", "address": "3625 DISCOVERY DR Boulder CO", "date": "03/03/2018 23:09 - 03/04/2018 01:24"}}
{"2018-00000747": {"category": "Other", "address": "3625 DISCOVERY DR Boulder CO", "date": "03/03/2018 23:09 - 03/04/2018 01:24"}}
{"2018-00000747": {"category": "Other", "address": "3625 DISCOVERY DR Boulder CO", "date": "03/03/2018 23:09 - 03/04/2018 01:24"}}
{"2018-00000748": {"category": "Traffic", "address": "900 REGENT DR Boulder CO", "date": "03/03/2018 23:12 - 03/03/2018 23:12"}}
{"2018-00000748": {"category": "Traffic", "address": "900 REGENT DR Boulder CO", "date": "03/03/2018 23:12 - 03/03/2018 23:12"}}
{"2018-00000748": {"category": "Traffic", "address": "900 REGENT DR Boulder CO", "date": "03/03/2018 23:12 - 03/03/2018 23:12"}}
{"2018-00000748": {"category": "Traffic", "address": "900 REGENT DR Boulder CO", "date": "03/03/2018 23:12 - 03/03/2018 23:12"}}
{"2018-00000749": {"category": "Warrant", "address": "1720 UNIVERSITY AVE Boulder CO", "date": "03/03/2018 23:58 - 03/03/2018 23:58"}}
{"2018-00000679": {"category": "Drug", "address": "2200 BAKER DR Boulder CO", "date": "02/26/2018 21:06 - 02/26/2018 21:06"}}
{"2018-00000679": {"category": "Drug", "address": "2200 BAKER DR Boulder CO", "date": "02/26/2018 21:06 - 02/26/2018 21:06"}}
{"2018-00000680": {"category": "Drug", "address": "1720 UNIVERSITY AVE Boulder CO", "date": "02/26/2018 23:01 - 02/26/2018 23:24"}}
{"2018-00008142": {"category": "Theft", "address": "1255 18TH ST Boulder CO", "date": "02/23/2018 18:00 - 02/26/2018 07:30"}}
{"2018-00008146": {"category": "Criminal", "address": "2575 KITTREDGE LOOP DR Boulder CO", "date": "02/25/2018 18:00 - 02/26/2018 15:30"}}
{"2018-00000244": {"category": "Traffic", "address": "1995 COLORADO AVE Boulder CO", "date": "01/17/2018 06:20 - 01/17/2018 06:20"}}
{"2018-00000336": {"category": "Criminal", "address": "1720 UNIVERSITY AVE Boulder CO", "date": "02/02/2018 20:28 - 02/02/2018 20:28"}}
{"2018-00000336": {"category": "Criminal", "address": "1720 UNIVERSITY AVE Boulder CO", "date": "02/02/2018 20:28 - 02/02/2018 20:28"}}
{"2018-00000377": {"category": "Drug", "address": "960 GREEN MOUNTAIN DR Boulder CO", "date": "02/06/2018 00:00 - 02/06/2018 00:50"}}
{"2018-00000377": {"category": "Drug", "address": "960 GREEN MOUNTAIN DR Boulder CO", "date": "02/06/2018 00:00 - 02/06/2018 00:50"}}
{"2018-00000377": {"category": "Drug", "address": "960 GREEN MOUNTAIN DR Boulder CO", "date": "02/06/2018 00:00 - 02/06/2018 00:50"}}
{"2018-00000378": {"category": "Alcohol", "address": "1720 UNIVERSITY AVE Boulder CO", "date": "02/06/2018 00:26 - 02/06/2018 00:49"}}
{"2018-00000380": {"category": "Drug", "address": "1720 UNIVERSITY AVE Boulder CO", "date": "02/06/2018 00:54 - 02/06/2018 01:14"}}
{"2018-00000383": {"category": "Harassment", "address": "1669 EUCLID AVE Boulder CO", "date": "02/06/2018 18:30 - 02/06/2018 18:30"}}
{"2018-00000383": {"category": "Harassment", "address": "1669 EUCLID AVE Boulder CO", "date": "02/06/2018 18:30 - 02/06/2018 18:30"}}
{"2018-00000385": {"category": "Fraud/Forgery", "address": "1855 ATHENS ST Boulder CO", "date": "02/06/2018 20:00 - 02/06/2018 20:00"}}
{"2018-00000386": {"category": "Drug", "address": "2200 BAKER DR Boulder CO", "date": "02/06/2018 19:53 - 02/06/2018 20:38"}}
{"2018-00000387": {"category": "Drug", "address": "600 30TH ST Boulder CO", "date": "02/06/2018 22:08 - 02/06/2018 22:08"}}
{"2018-00000387": {"category": "Drug", "address": "600 30TH ST Boulder CO", "date": "02/06/2018 22:08 - 02/06/2018 22:08"}}
{"2018-00000186": {"category": "Sex", "address": "2320 LIBBY DR Boulder CO", "date": "01/21/2018 02:00 - 01/21/2018 02:00"}}
{"2018-00000244": {"category": "Traffic", "address": "1995 COLORADO AVE Boulder CO", "date": "01/17/2018 06:20 - 01/17/2018 06:20"}}
{"2018-00000284": {"category": "Traffic", "address": "30TH ST /  BASELINE RD Boulder CO", "date": "01/29/2018 22:55 - 01/30/2018 00:20"}}
{"2018-00000284": {"category": "Traffic", "address": "30TH ST /  BASELINE RD Boulder CO", "date": "01/29/2018 22:55 - 01/30/2018 00:20"}}
{"2018-00000286": {"category": "Warrant", "address": "28TH ST /  COLORADO AVE Boulder CO", "date": "01/30/2018 03:56 - 01/30/2018 04:05"}}
{"2018-00000286": {"category": "Warrant", "address": "28TH ST /  COLORADO AVE Boulder CO", "date": "01/30/2018 03:56 - 01/30/2018 04:05"}}
{"2018-00000291": {"category": "Theft", "address": "1669 EUCLID AVE Boulder CO", "date": "01/30/2018 17:25 - 01/30/2018 17:25"}}
{"2018-00000292": {"category": "Theft", "address": "1040 REGENT DR Boulder CO", "date": "01/30/2018 12:30 - 01/30/2018 20:30"}}
{"2018-00000293": {"category": "Drug", "address": "600 30TH ST Boulder CO", "date": "01/30/2018 20:18 - 01/30/2018 20:54"}}
{"2018-00000293": {"category": "Drug", "address": "600 30TH ST Boulder CO", "date": "01/30/2018 20:18 - 01/30/2018 20:54"}}
{"2018-00000294": {"category": "Drug", "address": "960 GREEN MOUNTAIN DR Boulder CO", "date": "01/30/2018 20:38 - 01/30/2018 21:02"}}
{"2018-00008070": {"category": "Theft", "address": "1835 PLEASANT ST Boulder CO", "date": "01/29/2018 13:35 - 01/29/2018 14:50"}}
{"2018-00008071": {"category": "Theft", "address": "2450 KITTREDGE LOOP DR Boulder CO", "date": "01/30/2018 18:25 - 01/30/2018 18:25"}}
{"2018-00008072": {"category": "Theft", "address": "1499 CENTRAL CAMPUS Boulder CO", "date": "12/17/2017 18:05 - 01/10/2018 18:05"}}
{"2018-00008075": {"category": "Accident", "address": "995 REGENT DR Boulder CO", "date": "01/30/2018 17:05 - 01/30/2018 17:05"}}
{"2018-00000461": {"category": "Alcohol", "address": "600 30TH ST Boulder CO", "date": "02/11/2018 00:06 - 02/11/2018 00:35"}}
{"2018-00000462": {"category": "Alcohol", "address": "600 30TH ST Boulder CO", "date": "02/10/2018 00:37 - 02/11/2018 01:02"}}
{"2018-00000463": {"category": "Other", "address": "2605 KITTREDGE LOOP DR Boulder CO", "date": "02/11/2018 02:00 - 02/11/2018 02:00"}}
{"2018-00000463": {"category": "Other", "address": "2605 KITTREDGE LOOP DR Boulder CO", "date": "02/11/2018 02:00 - 02/11/2018 02:00"}}
{"2018-00000464": {"category": "Other", "address": "1720 UNIVERSITY AVE Boulder CO", "date": "02/11/2018 13:28 - 02/11/2018 13:28"}}
{"2018-00000465": {"category": "Harassment", "address": "1050 REGENT DR Boulder CO", "date": "02/11/2018 14:14 - 02/11/2018 14:14"}}
{"2018-00000467": {"category": "Drug", "address": "600 30TH ST Boulder CO", "date": "02/11/2018 20:05 - 02/11/2018 20:34"}}
{"2018-00000467": {"category": "Drug", "address": "600 30TH ST Boulder CO", "date": "02/11/2018 20:05 - 02/11/2018 20:34"}}
{"2018-00000312": {"category": "Burglary", "address": "1720 UNIVERSITY AVE Boulder CO", "date": "02/01/2018 14:00 - 02/01/2018 16:00"}}
{"2018-00000312": {"category": "Burglary", "address": "1720 UNIVERSITY AVE Boulder CO", "date": "02/01/2018 14:00 - 02/01/2018 16:00"}}
{"2018-00000627": {"category": "DUI/DWAI", "address": "27TH WAY /  BASELINE RD Boulder CO", "date": "02/22/2018 00:48 - 02/22/2018 00:48"}}
{"2018-00000627": {"category": "DUI/DWAI", "address": "27TH WAY /  BASELINE RD Boulder CO", "date": "02/22/2018 00:48 - 02/22/2018 00:48"}}
{"2018-00000627": {"category": "DUI/DWAI", "address": "27TH WAY /  BASELINE RD Boulder CO", "date": "02/22/2018 00:48 - 02/22/2018 00:48"}}
{"2018-00000627": {"category": "DUI/DWAI", "address": "27TH WAY /  BASELINE RD Boulder CO", "date": "02/22/2018 00:48 - 02/22/2018 00:48"}}
{"2018-00000628": {"category": "Criminal", "address": "2005 BAKER DR Boulder CO", "date": "02/22/2018 01:05 - 02/22/2018 01:15"}}
{"2018-00000629": {"category": "Traffic", "address": "27TH WAY /  BASELINE RD Boulder CO", "date": "02/22/2018 03:30 - 02/22/2018 03:30"}}
{"2018-00000629": {"category": "Traffic", "address": "27TH WAY /  BASELINE RD Boulder CO", "date": "02/22/2018 03:30 - 02/22/2018 03:30"}}
{"2018-00000629": {"category": "Traffic", "address": "27TH WAY /  BASELINE RD Boulder CO", "date": "02/22/2018 03:30 - 02/22/2018 03:30"}}
{"2018-00000630": {"category": "Traffic", "address": "995 REGENT DR Boulder CO", "date": "02/22/2018 10:30 - 02/22/2018 10:30"}}
{"2018-00000633": {"category": "Alcohol", "address": "2200 WILLARD LOOP DR Boulder CO", "date": "02/22/2018 22:29 - 02/22/2018 22:29"}}
{"2018-00008132": {"category": "Theft", "address": "1610 PLEASANT ST Boulder CO", "date": "02/22/2018 13:40 - 02/22/2018 13:40"}}
